{"income_statements":[{"period_end":"2009-12-31","period_type":"A","fiscal_year":2011,"fiscal_quarter":null,"revenue":null,"gross_profit":235850000.0,"operating_income":98512000.0,"net_income":43055000.0,"eps_diluted":null},{"period_end":"2010-06-30","period_type":"Q","fiscal_year":2011,"fiscal_quarter":2,"revenue":null,"gross_profit":106163000.0,"operating_income":34318000.0,"net_income":15302000.0,"eps_diluted":-2.71},{"period_end":"2010-09-30","period_type":"Q","fiscal_year":2011,"fiscal_quarter":3,"revenue":null,"gross_profit":173525000.0,"operating_income":64088000.0,"net_income":38300000.0,"eps_diluted":null},{"period_end":"2010-12-31","period_type":"A","fiscal_year":2012,"fiscal_quarter":null,"revenue":null,"gross_profit":237357000.0,"operating_income":90296000.0,"net_income":56913000.0,"eps_diluted":null},{"period_end":"2011-03-31","period_type":"A","fiscal_year":2012,"fiscal_quarter":null,"revenue":null,"gross_profit":47177000.0,"operating_income":11143000.0,"net_income":4844000.0,"eps_diluted":0.07},{"period_end":"2011-03-31","period_type":"Q","fiscal_year":2012,"fiscal_quarter":1,"revenue":null,"gross_profit":47177000.0,"operating_income":11143000.0,"net_income":4844000.0,"eps_diluted":0.07},{"period_end":"2011-06-30","period_type":"A","fiscal_year":2012,"fiscal_quarter":null,"revenue":null,"gross_profit":60353000.0,"operating_income":21800000.0,"net_income":15289000.0,"eps_diluted":0.23},{"period_end":"2011-06-30","period_type":"Q","fiscal_year":2012,"fiscal_quarter":2,"revenue":null,"gross_profit":107530000.0,"operating_income":32943000.0,"net_income":20133000.0,"eps_diluted":0.3},{"period_end":"2011-09-30","period_type":"A","fiscal_year":2012,"fiscal_quarter":null,"revenue":null,"gross_profit":88659000.0,"operating_income":44178000.0,"net_income":37379000.0,"eps_diluted":0.55},{"period_end":"2011-09-30","period_type":"Q","fiscal_year":2011,"fiscal_quarter":3,"revenue":null,"gross_profit":196189000.0,"operating_income":77121000.0,"net_income":57512000.0,"eps_diluted":null},{"period_end":"2011-12-31","period_type":"A","fiscal_year":2013,"fiscal_quarter":null,"revenue":null,"gross_profit":294654000.0,"operating_income":112981000.0,"net_income":324643000.0,"eps_diluted":4.79},{"period_end":"2012-03-31","period_type":"A","fiscal_year":2013,"fiscal_quarter":null,"revenue":null,"gross_profit":111005000.0,"operating_income":59493000.0,"net_income":30060000.0,"eps_diluted":0.44},{"period_end":"2012-03-31","period_type":"Q","fiscal_year":2013,"fiscal_quarter":1,"revenue":null,"gross_profit":111005000.0,"operating_income":59493000.0,"net_income":30060000.0,"eps_diluted":0.44},{"period_end":"2012-06-30","period_type":"A","fiscal_year":2013,"fiscal_quarter":null,"revenue":null,"gross_profit":87429000.0,"operating_income":37158000.0,"net_income":9335000.0,"eps_diluted":0.14},{"period_end":"2012-06-30","period_type":"Q","fiscal_year":2013,"fiscal_quarter":2,"revenue":null,"gross_profit":198434000.0,"operating_income":96651000.0,"net_income":39395000.0,"eps_diluted":0.57},{"period_end":"2012-09-30","period_type":"A","fiscal_year":2013,"fiscal_quarter":null,"revenue":null,"gross_profit":115813000.0,"operating_income":59124000.0,"net_income":25541000.0,"eps_diluted":0.37},{"period_end":"2012-09-30","period_type":"Q","fiscal_year":2013,"fiscal_quarter":3,"revenue":null,"gross_profit":314247000.0,"operating_income":155775000.0,"net_income":64936000.0,"eps_diluted":0.94},{"period_end":"2012-12-31","period_type":"A","fiscal_year":2014,"fiscal_quarter":null,"revenue":1176306000.0,"gross_profit":440400000.0,"operating_income":223555000.0,"net_income":93223000.0,"eps_diluted":1.35},{"period_end":"2013-03-31","period_type":"A","fiscal_year":2014,"fiscal_quarter":null,"revenue":399572000.0,"gross_profit":153462000.0,"operating_income":96525000.0,"net_income":50674000.0,"eps_diluted":0.73},{"period_end":"2013-03-31","period_type":"Q","fiscal_year":2014,"fiscal_quarter":1,"revenue":null,"gross_profit":153462000.0,"operating_income":96525000.0,"net_income":50674000.0,"eps_diluted":0.73},{"period_end":"2013-06-30","period_type":"A","fiscal_year":2014,"fiscal_quarter":null,"revenue":346688000.0,"gross_profit":130953000.0,"operating_income":76433000.0,"net_income":28254000.0,"eps_diluted":0.4},{"period_end":"2013-06-30","period_type":"Q","fiscal_year":2014,"fiscal_quarter":2,"revenue":746260000.0,"gross_profit":284415000.0,"operating_income":172958000.0,"net_income":78928000.0,"eps_diluted":1.13},{"period_end":"2013-09-30","period_type":"A","fiscal_year":2014,"fiscal_quarter":null,"revenue":363269000.0,"gross_profit":139463000.0,"operating_income":87289000.0,"net_income":47093000.0,"eps_diluted":0.67},{"period_end":"2013-09-30","period_type":"Q","fiscal_year":2014,"fiscal_quarter":3,"revenue":1109529000.0,"gross_profit":423878000.0,"operating_income":260247000.0,"net_income":126021000.0,"eps_diluted":1.81},{"period_end":"2013-12-31","period_type":"A","fiscal_year":2015,"fiscal_quarter":null,"revenue":1485765000.0,"gross_profit":569560000.0,"operating_income":351465000.0,"net_income":174539000.0,"eps_diluted":2.51},{"period_end":"2014-03-31","period_type":"A","fiscal_year":2015,"fiscal_quarter":null,"revenue":342008000.0,"gross_profit":119514000.0,"operating_income":65306000.0,"net_income":34701000.0,"eps_diluted":0.5},{"period_end":"2014-03-31","period_type":"Q","fiscal_year":2015,"fiscal_quarter":1,"revenue":342008000.0,"gross_profit":119514000.0,"operating_income":65306000.0,"net_income":34701000.0,"eps_diluted":0.5},{"period_end":"2014-06-30","period_type":"A","fiscal_year":2015,"fiscal_quarter":null,"revenue":362609000.0,"gross_profit":128012000.0,"operating_income":78160000.0,"net_income":54025000.0,"eps_diluted":0.77},{"period_end":"2014-06-30","period_type":"Q","fiscal_year":2015,"fiscal_quarter":2,"revenue":704617000.0,"gross_profit":247526000.0,"operating_income":143466000.0,"net_income":88726000.0,"eps_diluted":1.27},{"period_end":"2014-09-30","period_type":"A","fiscal_year":2015,"fiscal_quarter":null,"revenue":352305000.0,"gross_profit":130283000.0,"operating_income":70794000.0,"net_income":36497000.0,"eps_diluted":0.52},{"period_end":"2014-09-30","period_type":"Q","fiscal_year":2015,"fiscal_quarter":3,"revenue":1056922000.0,"gross_profit":377809000.0,"operating_income":214260000.0,"net_income":125223000.0,"eps_diluted":1.79},{"period_end":"2014-12-31","period_type":"A","fiscal_year":2016,"fiscal_quarter":null,"revenue":1460919000.0,"gross_profit":516219000.0,"operating_income":293375000.0,"net_income":174613000.0,"eps_diluted":2.49},{"period_end":"2015-03-31","period_type":"A","fiscal_year":2016,"fiscal_quarter":null,"revenue":311818000.0,"gross_profit":102603000.0,"operating_income":44911000.0,"net_income":19685000.0,"eps_diluted":0.28},{"period_end":"2015-03-31","period_type":"Q","fiscal_year":2016,"fiscal_quarter":1,"revenue":311818000.0,"gross_profit":102603000.0,"operating_income":44911000.0,"net_income":19685000.0,"eps_diluted":0.28},{"period_end":"2015-06-30","period_type":"A","fiscal_year":2016,"fiscal_quarter":null,"revenue":288360000.0,"gross_profit":95897000.0,"operating_income":39467000.0,"net_income":14844000.0,"eps_diluted":0.21},{"period_end":"2015-06-30","period_type":"Q","fiscal_year":2016,"fiscal_quarter":2,"revenue":600178000.0,"gross_profit":198500000.0,"operating_income":84378000.0,"net_income":34529000.0,"eps_diluted":0.49},{"period_end":"2015-09-30","period_type":"A","fiscal_year":2016,"fiscal_quarter":null,"revenue":359291000.0,"gross_profit":130326000.0,"operating_income":67867000.0,"net_income":34036000.0,"eps_diluted":0.49},{"period_end":"2015-09-30","period_type":"Q","fiscal_year":2016,"fiscal_quarter":3,"revenue":959469000.0,"gross_profit":328826000.0,"operating_income":152245000.0,"net_income":68565000.0,"eps_diluted":0.98},{"period_end":"2015-12-31","period_type":"A","fiscal_year":2017,"fiscal_quarter":null,"revenue":1317299000.0,"gross_profit":459950000.0,"operating_income":179561000.0,"net_income":77747000.0,"eps_diluted":1.12},{"period_end":"2016-03-31","period_type":"A","fiscal_year":2017,"fiscal_quarter":null,"revenue":286535000.0,"gross_profit":98060000.0,"operating_income":26964000.0,"net_income":10208000.0,"eps_diluted":0.15},{"period_end":"2016-03-31","period_type":"Q","fiscal_year":2017,"fiscal_quarter":1,"revenue":286535000.0,"gross_profit":98060000.0,"operating_income":26964000.0,"net_income":10208000.0,"eps_diluted":0.15},{"period_end":"2016-06-30","period_type":"A","fiscal_year":2017,"fiscal_quarter":null,"revenue":367376000.0,"gross_profit":124147000.0,"operating_income":44082000.0,"net_income":20888000.0,"eps_diluted":0.31},{"period_end":"2016-06-30","period_type":"Q","fiscal_year":2017,"fiscal_quarter":2,"revenue":653911000.0,"gross_profit":222207000.0,"operating_income":71046000.0,"net_income":31096000.0,"eps_diluted":0.47},{"period_end":"2016-09-30","period_type":"A","fiscal_year":2017,"fiscal_quarter":null,"revenue":373121000.0,"gross_profit":137772000.0,"operating_income":56340000.0,"net_income":26183000.0,"eps_diluted":0.4},{"period_end":"2016-09-30","period_type":"Q","fiscal_year":2017,"fiscal_quarter":3,"revenue":1027032000.0,"gross_profit":359979000.0,"operating_income":127386000.0,"net_income":57279000.0,"eps_diluted":0.87},{"period_end":"2016-12-31","period_type":"A","fiscal_year":2018,"fiscal_quarter":null,"revenue":1447743000.0,"gross_profit":512421000.0,"operating_income":202752000.0,"net_income":97154000.0,"eps_diluted":1.47},{"period_end":"2017-03-31","period_type":"A","fiscal_year":2018,"fiscal_quarter":null,"revenue":332056000.0,"gross_profit":109954000.0,"operating_income":30890000.0,"net_income":12175000.0,"eps_diluted":0.2},{"period_end":"2017-03-31","period_type":"Q","fiscal_year":2017,"fiscal_quarter":1,"revenue":331814000.0,"gross_profit":108800000.0,"operating_income":30890000.0,"net_income":12175000.0,"eps_diluted":0.2},{"period_end":"2017-06-30","period_type":"A","fiscal_year":2018,"fiscal_quarter":null,"revenue":396523000.0,"gross_profit":134224000.0,"operating_income":51822000.0,"net_income":25291000.0,"eps_diluted":0.41},{"period_end":"2017-06-30","period_type":"Q","fiscal_year":2018,"fiscal_quarter":2,"revenue":725360000.0,"gross_profit":241721000.0,"operating_income":82712000.0,"net_income":37466000.0,"eps_diluted":0.61},{"period_end":"2017-09-30","period_type":"A","fiscal_year":2018,"fiscal_quarter":null,"revenue":457747000.0,"gross_profit":157680000.0,"operating_income":72548000.0,"net_income":39435000.0,"eps_diluted":0.63},{"period_end":"2017-09-30","period_type":"Q","fiscal_year":2018,"fiscal_quarter":3,"revenue":1181199000.0,"gross_profit":397952000.0,"operating_income":155260000.0,"net_income":76901000.0,"eps_diluted":1.24},{"period_end":"2017-12-31","period_type":"A","fiscal_year":2019,"fiscal_quarter":null,"revenue":1679373000.0,"gross_profit":584786000.0,"operating_income":250634000.0,"net_income":157808000.0,"eps_diluted":2.53},{"period_end":"2018-03-31","period_type":"A","fiscal_year":2019,"fiscal_quarter":null,"revenue":400091000.0,"gross_profit":141927000.0,"operating_income":56347000.0,"net_income":33645000.0,"eps_diluted":0.42},{"period_end":"2018-03-31","period_type":"Q","fiscal_year":2019,"fiscal_quarter":1,"revenue":400091000.0,"gross_profit":141927000.0,"operating_income":56347000.0,"net_income":33645000.0,"eps_diluted":0.42},{"period_end":"2018-06-30","period_type":"A","fiscal_year":2019,"fiscal_quarter":null,"revenue":497581000.0,"gross_profit":178473000.0,"operating_income":85467000.0,"net_income":53261000.0,"eps_diluted":0.82},{"period_end":"2018-06-30","period_type":"Q","fiscal_year":2019,"fiscal_quarter":2,"revenue":897672000.0,"gross_profit":320400000.0,"operating_income":141814000.0,"net_income":86906000.0,"eps_diluted":1.24},{"period_end":"2018-09-30","period_type":"A","fiscal_year":2019,"fiscal_quarter":null,"revenue":562388000.0,"gross_profit":200334000.0,"operating_income":106519000.0,"net_income":75776000.0,"eps_diluted":1.11},{"period_end":"2018-09-30","period_type":"Q","fiscal_year":2019,"fiscal_quarter":3,"revenue":1460060000.0,"gross_profit":520734000.0,"operating_income":248333000.0,"net_income":162682000.0,"eps_diluted":2.34},{"period_end":"2018-12-31","period_type":"A","fiscal_year":2020,"fiscal_quarter":null,"revenue":2023464000.0,"gross_profit":725040000.0,"operating_income":357181000.0,"net_income":238257000.0,"eps_diluted":3.54},{"period_end":"2019-03-31","period_type":"A","fiscal_year":2020,"fiscal_quarter":null,"revenue":470353000.0,"gross_profit":162175000.0,"operating_income":71173000.0,"net_income":44861000.0,"eps_diluted":0.76},{"period_end":"2019-03-31","period_type":"Q","fiscal_year":2020,"fiscal_quarter":1,"revenue":470353000.0,"gross_profit":162175000.0,"operating_income":71173000.0,"net_income":44861000.0,"eps_diluted":0.76},{"period_end":"2019-06-30","period_type":"A","fiscal_year":2020,"fiscal_quarter":null,"revenue":541916000.0,"gross_profit":195838000.0,"operating_income":90926000.0,"net_income":61958000.0,"eps_diluted":0.98},{"period_end":"2019-06-30","period_type":"Q","fiscal_year":2020,"fiscal_quarter":2,"revenue":1012269000.0,"gross_profit":358013000.0,"operating_income":162099000.0,"net_income":106819000.0,"eps_diluted":1.74},{"period_end":"2019-09-30","period_type":"A","fiscal_year":2020,"fiscal_quarter":null,"revenue":601135000.0,"gross_profit":217517000.0,"operating_income":105556000.0,"net_income":75574000.0,"eps_diluted":1.18},{"period_end":"2019-09-30","period_type":"Q","fiscal_year":2020,"fiscal_quarter":3,"revenue":1613404000.0,"gross_profit":575530000.0,"operating_income":267655000.0,"net_income":182393000.0,"eps_diluted":2.92},{"period_end":"2019-12-31","period_type":"A","fiscal_year":2021,"fiscal_quarter":null,"revenue":2204336000.0,"gross_profit":797752000.0,"operating_income":372163000.0,"net_income":252007000.0,"eps_diluted":4.03},{"period_end":"2020-03-31","period_type":"A","fiscal_year":2021,"fiscal_quarter":null,"revenue":475915000.0,"gross_profit":172320000.0,"operating_income":62862000.0,"net_income":44460000.0,"eps_diluted":0.68},{"period_end":"2020-03-31","period_type":"Q","fiscal_year":2021,"fiscal_quarter":1,"revenue":475915000.0,"gross_profit":172320000.0,"operating_income":62862000.0,"net_income":44460000.0,"eps_diluted":0.68},{"period_end":"2020-06-30","period_type":"A","fiscal_year":2021,"fiscal_quarter":null,"revenue":546848000.0,"gross_profit":208983000.0,"operating_income":89553000.0,"net_income":66145000.0,"eps_diluted":1.02},{"period_end":"2020-06-30","period_type":"Q","fiscal_year":2021,"fiscal_quarter":2,"revenue":1022763000.0,"gross_profit":381303000.0,"operating_income":152415000.0,"net_income":110605000.0,"eps_diluted":1.7},{"period_end":"2020-09-30","period_type":"A","fiscal_year":2021,"fiscal_quarter":null,"revenue":701355000.0,"gross_profit":276149000.0,"operating_income":155637000.0,"net_income":114970000.0,"eps_diluted":1.82},{"period_end":"2020-09-30","period_type":"Q","fiscal_year":2021,"fiscal_quarter":3,"revenue":1724118000.0,"gross_profit":657452000.0,"operating_income":308052000.0,"net_income":225575000.0,"eps_diluted":3.51},{"period_end":"2020-12-31","period_type":"A","fiscal_year":2022,"fiscal_quarter":null,"revenue":2485200000.0,"gross_profit":957654000.0,"operating_income":479106000.0,"net_income":350576000.0,"eps_diluted":5.48},{"period_end":"2021-03-31","period_type":"A","fiscal_year":2022,"fiscal_quarter":null,"revenue":807434000.0,"gross_profit":321814000.0,"operating_income":189124000.0,"net_income":148993000.0,"eps_diluted":2.33},{"period_end":"2021-03-31","period_type":"Q","fiscal_year":2022,"fiscal_quarter":1,"revenue":807434000.0,"gross_profit":321814000.0,"operating_income":189124000.0,"net_income":148993000.0,"eps_diluted":2.33},{"period_end":"2021-06-30","period_type":"A","fiscal_year":2022,"fiscal_quarter":null,"revenue":919981000.0,"gross_profit":339735000.0,"operating_income":182952000.0,"net_income":127036000.0,"eps_diluted":2.01},{"period_end":"2021-06-30","period_type":"Q","fiscal_year":2022,"fiscal_quarter":2,"revenue":1727415000.0,"gross_profit":661549000.0,"operating_income":372076000.0,"net_income":276029000.0,"eps_diluted":4.34},{"period_end":"2021-09-30","period_type":"A","fiscal_year":2022,"fiscal_quarter":null,"revenue":942698000.0,"gross_profit":335994000.0,"operating_income":173579000.0,"net_income":131570000.0,"eps_diluted":1.93},{"period_end":"2021-09-30","period_type":"Q","fiscal_year":2022,"fiscal_quarter":3,"revenue":2670113000.0,"gross_profit":997543000.0,"operating_income":545655000.0,"net_income":407599000.0,"eps_diluted":6.27},{"period_end":"2021-12-31","period_type":"A","fiscal_year":2023,"fiscal_quarter":null,"revenue":3737184000.0,"gross_profit":1360082000.0,"operating_income":721136000.0,"net_income":550494000.0,"eps_diluted":8.3},{"period_end":"2022-03-31","period_type":"A","fiscal_year":2023,"fiscal_quarter":null,"revenue":1135856000.0,"gross_profit":360748000.0,"operating_income":154735000.0,"net_income":113858000.0,"eps_diluted":1.57},{"period_end":"2022-03-31","period_type":"Q","fiscal_year":2023,"fiscal_quarter":1,"revenue":1135856000.0,"gross_profit":360748000.0,"operating_income":154735000.0,"net_income":113858000.0,"eps_diluted":1.57},{"period_end":"2022-06-30","period_type":"A","fiscal_year":2023,"fiscal_quarter":null,"revenue":1291391000.0,"gross_profit":456985000.0,"operating_income":216844000.0,"net_income":156359000.0,"eps_diluted":2.21},{"period_end":"2022-06-30","period_type":"Q","fiscal_year":2023,"fiscal_quarter":2,"revenue":2427247000.0,"gross_profit":817733000.0,"operating_income":371579000.0,"net_income":270217000.0,"eps_diluted":3.78},{"period_end":"2022-09-30","period_type":"A","fiscal_year":2023,"fiscal_quarter":null,"revenue":1088258000.0,"gross_profit":361104000.0,"operating_income":87523000.0,"net_income":58270000.0,"eps_diluted":0.83},{"period_end":"2022-09-30","period_type":"Q","fiscal_year":2023,"fiscal_quarter":3,"revenue":3515505000.0,"gross_profit":1178837000.0,"operating_income":459102000.0,"net_income":328487000.0,"eps_diluted":4.61},{"period_end":"2022-12-31","period_type":"A","fiscal_year":2024,"fiscal_quarter":null,"revenue":4564737000.0,"gross_profit":1522004000.0,"operating_income":566330000.0,"net_income":399502000.0,"eps_diluted":5.42},{"period_end":"2023-03-31","period_type":"A","fiscal_year":2023,"fiscal_quarter":null,"revenue":887910000.0,"gross_profit":272499000.0,"operating_income":44483000.0,"net_income":12430000.0,"eps_diluted":0.05},{"period_end":"2023-03-31","period_type":"Q","fiscal_year":2024,"fiscal_quarter":1,"revenue":887910000.0,"gross_profit":272499000.0,"operating_income":44483000.0,"net_income":12430000.0,"eps_diluted":0.05},{"period_end":"2023-06-30","period_type":"A","fiscal_year":2023,"fiscal_quarter":null,"revenue":1000420000.0,"gross_profit":328421000.0,"operating_income":85972000.0,"net_income":45198000.0,"eps_diluted":0.7},{"period_end":"2023-06-30","period_type":"Q","fiscal_year":2024,"fiscal_quarter":2,"revenue":1888330000.0,"gross_profit":600920000.0,"operating_income":130455000.0,"net_income":57628000.0,"eps_diluted":0.75},{"period_end":"2023-09-30","period_type":"A","fiscal_year":2023,"fiscal_quarter":null,"revenue":1070667000.0,"gross_profit":375787000.0,"operating_income":104776000.0,"net_income":60377000.0,"eps_diluted":0.97},{"period_end":"2023-09-30","period_type":"Q","fiscal_year":2024,"fiscal_quarter":3,"revenue":2958997000.0,"gross_profit":976707000.0,"operating_income":235231000.0,"net_income":118005000.0,"eps_diluted":1.72},{"period_end":"2023-12-31","period_type":"A","fiscal_year":2025,"fiscal_quarter":null,"revenue":4022667000.0,"gross_profit":1365431000.0,"operating_income":386199000.0,"net_income":214606000.0,"eps_diluted":3.27},{"period_end":"2024-03-31","period_type":"Q","fiscal_year":2025,"fiscal_quarter":1,"revenue":889273000.0,"gross_profit":316379000.0,"operating_income":66869000.0,"net_income":26232000.0,"eps_diluted":0.39},{"period_end":"2024-06-30","period_type":"Q","fiscal_year":2025,"fiscal_quarter":2,"revenue":1887470000.0,"gross_profit":691940000.0,"operating_income":170104000.0,"net_income":85347000.0,"eps_diluted":1.36},{"period_end":"2024-09-30","period_type":"Q","fiscal_year":2025,"fiscal_quarter":3,"revenue":3061033000.0,"gross_profit":1164209000.0,"operating_income":338728000.0,"net_income":199089000.0,"eps_diluted":3.25},{"period_end":"2024-12-31","period_type":"A","fiscal_year":2025,"fiscal_quarter":null,"revenue":4295834000.0,"gross_profit":1665626000.0,"operating_income":536742000.0,"net_income":316315000.0,"eps_diluted":5.39},{"period_end":"2025-03-31","period_type":"Q","fiscal_year":2025,"fiscal_quarter":1,"revenue":942121000.0,"gross_profit":371986000.0,"operating_income":83638000.0,"net_income":43840000.0,"eps_diluted":0.73},{"period_end":"2025-06-30","period_type":"Q","fiscal_year":2025,"fiscal_quarter":2,"revenue":2003290000.0,"gross_profit":788735000.0,"operating_income":195427000.0,"net_income":117856000.0,"eps_diluted":1.98},{"period_end":"2025-09-30","period_type":"Q","fiscal_year":2025,"fiscal_quarter":3,"revenue":3117643000.0,"gross_profit":1215657000.0,"operating_income":298506000.0,"net_income":184017000.0,"eps_diluted":3.1},{"period_end":"2025-12-31","period_type":"A","fiscal_year":2025,"fiscal_quarter":null,"revenue":4209147000.0,"gross_profit":1611737000.0,"operating_income":289191000.0,"net_income":159554000.0,"eps_diluted":2.69}],"balance_sheets":[{"period_end":"2008-12-31","period_type":"A","cash":81229000.0,"total_assets":null,"long_term_debt":null,"total_liabilities":null,"stockholders_equity":-810194000.0},{"period_end":"2009-12-31","period_type":"A","cash":161307000.0,"total_assets":null,"long_term_debt":null,"total_liabilities":null,"stockholders_equity":-742814000.0},{"period_end":"2009-12-31","period_type":"Q","cash":161307000.0,"total_assets":null,"long_term_debt":null,"total_liabilities":null,"stockholders_equity":null},{"period_end":"2010-06-30","period_type":"Q","cash":93109000.0,"total_assets":null,"long_term_debt":null,"total_liabilities":null,"stockholders_equity":null},{"period_end":"2010-12-31","period_type":"A","cash":78583000.0,"total_assets":1209883000.0,"long_term_debt":657229000.0,"total_liabilities":768816000.0,"stockholders_equity":441067000.0},{"period_end":"2010-12-31","period_type":"Q","cash":78583000.0,"total_assets":1209883000.0,"long_term_debt":657229000.0,"total_liabilities":768816000.0,"stockholders_equity":441067000.0},{"period_end":"2011-03-31","period_type":"Q","cash":89997000.0,"total_assets":null,"long_term_debt":null,"total_liabilities":null,"stockholders_equity":null},{"period_end":"2011-06-30","period_type":"Q","cash":78746000.0,"total_assets":1212775000.0,"long_term_debt":632498000.0,"total_liabilities":749695000.0,"stockholders_equity":463080000.0},{"period_end":"2011-09-30","period_type":"Q","cash":138720000.0,"total_assets":1260376000.0,"long_term_debt":632498000.0,"total_liabilities":758515000.0,"stockholders_equity":501861000.0},{"period_end":"2011-12-31","period_type":"A","cash":93126000.0,"total_assets":1552793000.0,"long_term_debt":604372000.0,"total_liabilities":783904000.0,"stockholders_equity":768889000.0},{"period_end":"2011-12-31","period_type":"Q","cash":93126000.0,"total_assets":1552793000.0,"long_term_debt":575000000.0,"total_liabilities":783904000.0,"stockholders_equity":768889000.0},{"period_end":"2012-03-31","period_type":"Q","cash":91730000.0,"total_assets":1571717000.0,"long_term_debt":559588000.0,"total_liabilities":770944000.0,"stockholders_equity":800773000.0},{"period_end":"2012-06-30","period_type":"Q","cash":10307000.0,"total_assets":1491775000.0,"long_term_debt":875513000.0,"total_liabilities":1087169000.0,"stockholders_equity":404606000.0},{"period_end":"2012-09-30","period_type":"Q","cash":57966000.0,"total_assets":null,"long_term_debt":null,"total_liabilities":null,"stockholders_equity":null},{"period_end":"2012-12-31","period_type":"A","cash":108023000.0,"total_assets":1603847000.0,"long_term_debt":881268000.0,"total_liabilities":1140219000.0,"stockholders_equity":463628000.0},{"period_end":"2012-12-31","period_type":"Q","cash":108023000.0,"total_assets":1603847000.0,"long_term_debt":881268000.0,"total_liabilities":1140219000.0,"stockholders_equity":463628000.0},{"period_end":"2013-03-31","period_type":"Q","cash":54337000.0,"total_assets":1591726000.0,"long_term_debt":800702000.0,"total_liabilities":1076132000.0,"stockholders_equity":515594000.0},{"period_end":"2013-06-30","period_type":"Q","cash":126598000.0,"total_assets":1675367000.0,"long_term_debt":1186329000.0,"total_liabilities":1469426000.0,"stockholders_equity":205941000.0},{"period_end":"2013-09-30","period_type":"Q","cash":116521000.0,"total_assets":1733055000.0,"long_term_debt":null,"total_liabilities":1475715000.0,"stockholders_equity":257340000.0},{"period_end":"2013-12-31","period_type":"A","cash":150147000.0,"total_assets":1798205000.0,"long_term_debt":1197000000.0,"total_liabilities":1481134000.0,"stockholders_equity":317071000.0},{"period_end":"2013-12-31","period_type":"Q","cash":150147000.0,"total_assets":1798205000.0,"long_term_debt":null,"total_liabilities":1481134000.0,"stockholders_equity":317071000.0},{"period_end":"2014-03-31","period_type":"Q","cash":173740000.0,"total_assets":1812569000.0,"long_term_debt":null,"total_liabilities":1459525000.0,"stockholders_equity":353044000.0},{"period_end":"2014-06-30","period_type":"Q","cash":197959000.0,"total_assets":1829168000.0,"long_term_debt":1152331000.0,"total_liabilities":1420606000.0,"stockholders_equity":408562000.0},{"period_end":"2014-09-30","period_type":"Q","cash":173162000.0,"total_assets":1833904000.0,"long_term_debt":1104419000.0,"total_liabilities":1385987000.0,"stockholders_equity":447917000.0},{"period_end":"2014-12-31","period_type":"A","cash":189761000.0,"total_assets":1864419000.0,"long_term_debt":1080599000.0,"total_liabilities":1392743000.0,"stockholders_equity":489799000.0},{"period_end":"2014-12-31","period_type":"Q","cash":189761000.0,"total_assets":1882542000.0,"long_term_debt":null,"total_liabilities":1392743000.0,"stockholders_equity":489799000.0},{"period_end":"2015-03-31","period_type":"Q","cash":150085000.0,"total_assets":1842372000.0,"long_term_debt":1032326.0,"total_liabilities":1339679000.0,"stockholders_equity":502693000.0},{"period_end":"2015-06-30","period_type":"Q","cash":155575000.0,"total_assets":1871387000.0,"long_term_debt":933826.0,"total_liabilities":1351577000.0,"stockholders_equity":519810000.0},{"period_end":"2015-09-30","period_type":"Q","cash":46454000.0,"total_assets":1837579000.0,"long_term_debt":936646000.0,"total_liabilities":1348307000.0,"stockholders_equity":489272000.0},{"period_end":"2015-12-31","period_type":"A","cash":115857000.0,"total_assets":1778635000.0,"long_term_debt":937060000.0,"total_liabilities":1312764000.0,"stockholders_equity":465871000.0},{"period_end":"2015-12-31","period_type":"Q","cash":115857000.0,"total_assets":1778635000.0,"long_term_debt":null,"total_liabilities":1312764000.0,"stockholders_equity":465871000.0},{"period_end":"2016-03-31","period_type":"Q","cash":69370000.0,"total_assets":1933497000.0,"long_term_debt":null,"total_liabilities":1423991000.0,"stockholders_equity":474426000.0},{"period_end":"2016-06-30","period_type":"Q","cash":75641000.0,"total_assets":1916535000.0,"long_term_debt":null,"total_liabilities":1430512000.0,"stockholders_equity":450391000.0},{"period_end":"2016-09-30","period_type":"Q","cash":54163000.0,"total_assets":1868513000.0,"long_term_debt":null,"total_liabilities":1418386000.0,"stockholders_equity":413915000.0},{"period_end":"2016-12-31","period_type":"A","cash":67272000.0,"total_assets":1865969000.0,"long_term_debt":903673000.0,"total_liabilities":1427434000.0,"stockholders_equity":397179000.0},{"period_end":"2016-12-31","period_type":"Q","cash":67272000.0,"total_assets":1861684000.0,"long_term_debt":null,"total_liabilities":1427434000.0,"stockholders_equity":401122000.0},{"period_end":"2017-03-31","period_type":"Q","cash":57494000.0,"total_assets":1867265000.0,"long_term_debt":null,"total_liabilities":1413303000.0,"stockholders_equity":420467000.0},{"period_end":"2017-06-30","period_type":"Q","cash":67071000.0,"total_assets":1887530000.0,"long_term_debt":null,"total_liabilities":1421765000.0,"stockholders_equity":427922000.0},{"period_end":"2017-09-30","period_type":"Q","cash":128780000.0,"total_assets":2000974000.0,"long_term_debt":null,"total_liabilities":1485928000.0,"stockholders_equity":473147000.0},{"period_end":"2017-12-31","period_type":"A","cash":138472000.0,"total_assets":2025965000.0,"long_term_debt":935057000.0,"total_liabilities":1427716000.0,"stockholders_equity":554320000.0},{"period_end":"2017-12-31","period_type":"Q","cash":138472000.0,"total_assets":2025964000.0,"long_term_debt":null,"total_liabilities":1427716000.0,"stockholders_equity":554320000.0},{"period_end":"2018-03-31","period_type":"Q","cash":146162000.0,"total_assets":2077468000.0,"long_term_debt":null,"total_liabilities":1452870000.0,"stockholders_equity":570194000.0},{"period_end":"2018-06-30","period_type":"Q","cash":111714000.0,"total_assets":2209275000.0,"long_term_debt":null,"total_liabilities":1538985000.0,"stockholders_equity":617255000.0},{"period_end":"2018-09-30","period_type":"Q","cash":174001000.0,"total_assets":2332673000.0,"long_term_debt":null,"total_liabilities":1574141000.0,"stockholders_equity":698635000.0},{"period_end":"2018-12-31","period_type":"A","cash":224482000.0,"total_assets":2426314000.0,"long_term_debt":900813000.0,"total_liabilities":1604049000.0,"stockholders_equity":761261000.0},{"period_end":"2018-12-31","period_type":"Q","cash":224482000.0,"total_assets":2426314000.0,"long_term_debt":null,"total_liabilities":1604049000.0,"stockholders_equity":761261000.0},{"period_end":"2019-03-31","period_type":"Q","cash":161266000.0,"total_assets":2473722000.0,"long_term_debt":null,"total_liabilities":1606410000.0,"stockholders_equity":809955000.0},{"period_end":"2019-06-30","period_type":"Q","cash":110367000.0,"total_assets":2523109000.0,"long_term_debt":860083000.0,"total_liabilities":1592981000.0,"stockholders_equity":871011000.0},{"period_end":"2019-09-30","period_type":"Q","cash":216038000.0,"total_assets":2594121000.0,"long_term_debt":861231000.0,"total_liabilities":1598342000.0,"stockholders_equity":939215000.0},{"period_end":"2019-12-31","period_type":"A","cash":322883000.0,"total_assets":2665669000.0,"long_term_debt":832236000.0,"total_liabilities":1571591000.0,"stockholders_equity":1032851000.0},{"period_end":"2019-12-31","period_type":"Q","cash":322883000.0,"total_assets":2665669000.0,"long_term_debt":null,"total_liabilities":1571591000.0,"stockholders_equity":1032851000.0},{"period_end":"2020-03-31","period_type":"Q","cash":307456000.0,"total_assets":2654077000.0,"long_term_debt":813522000.0,"total_liabilities":1570486000.0,"stockholders_equity":1023687000.0},{"period_end":"2020-06-30","period_type":"Q","cash":396734000.0,"total_assets":2767625000.0,"long_term_debt":814094000.0,"total_liabilities":1609331000.0,"stockholders_equity":1097275000.0},{"period_end":"2020-09-30","period_type":"Q","cash":513944000.0,"total_assets":2974075000.0,"long_term_debt":814675.0,"total_liabilities":1680634000.0,"stockholders_equity":1229896000.0},{"period_end":"2020-12-31","period_type":"A","cash":655128000.0,"total_assets":3235423000.0,"long_term_debt":833990000.0,"total_liabilities":1779012000.0,"stockholders_equity":1390204000.0},{"period_end":"2020-12-31","period_type":"Q","cash":655128000.0,"total_assets":3235423000.0,"long_term_debt":null,"total_liabilities":1779012000.0,"stockholders_equity":1390204000.0},{"period_end":"2021-03-31","period_type":"Q","cash":744814000.0,"total_assets":3422138000.0,"long_term_debt":815835000.0,"total_liabilities":1834315000.0,"stockholders_equity":1524569000.0},{"period_end":"2021-06-30","period_type":"Q","cash":390086000.0,"total_assets":3706926000.0,"long_term_debt":766977000.0,"total_liabilities":2013743000.0,"stockholders_equity":1655938000.0},{"period_end":"2021-09-30","period_type":"Q","cash":423726000.0,"total_assets":4100430000.0,"long_term_debt":767547000.0,"total_liabilities":2273449000.0,"stockholders_equity":1782277000.0},{"period_end":"2021-12-31","period_type":"A","cash":147339000.0,"total_assets":4877780000.0,"long_term_debt":882060000.0,"total_liabilities":2605643000.0,"stockholders_equity":2214087000.0},{"period_end":"2021-12-31","period_type":"Q","cash":147339000.0,"total_assets":4877780000.0,"long_term_debt":null,"total_liabilities":2605643000.0,"stockholders_equity":2214087000.0},{"period_end":"2022-03-31","period_type":"Q","cash":206023000.0,"total_assets":5151533000.0,"long_term_debt":null,"total_liabilities":2771410000.0,"stockholders_equity":2308612000.0},{"period_end":"2022-06-30","period_type":"Q","cash":467140000.0,"total_assets":5472951000.0,"long_term_debt":null,"total_liabilities":2970359000.0,"stockholders_equity":2419762000.0},{"period_end":"2022-09-30","period_type":"Q","cash":229911000.0,"total_assets":5246293000.0,"long_term_debt":null,"total_liabilities":2839752000.0,"stockholders_equity":2319605000.0},{"period_end":"2022-12-31","period_type":"A","cash":132723000.0,"total_assets":5169462000.0,"long_term_debt":1370966000.0,"total_liabilities":2799736000.0,"stockholders_equity":2259255000.0},{"period_end":"2022-12-31","period_type":"Q","cash":132723000.0,"total_assets":5169462000.0,"long_term_debt":null,"total_liabilities":2799736000.0,"stockholders_equity":2259255000.0},{"period_end":"2023-03-31","period_type":"Q","cash":137365000.0,"total_assets":5211132000.0,"long_term_debt":1530000000.0,"total_liabilities":2865939000.0,"stockholders_equity":2341379000.0},{"period_end":"2023-06-30","period_type":"Q","cash":192768000.0,"total_assets":5321971000.0,"long_term_debt":1530000000.0,"total_liabilities":2894527000.0,"stockholders_equity":2421756000.0},{"period_end":"2023-09-30","period_type":"Q","cash":161525000.0,"total_assets":5166341000.0,"long_term_debt":1480000000.0,"total_liabilities":2794215000.0,"stockholders_equity":2366487000.0},{"period_end":"2023-12-31","period_type":"A","cash":200994000.0,"total_assets":5093312000.0,"long_term_debt":1434825000.0,"total_liabilities":2743693000.0,"stockholders_equity":2343070000.0},{"period_end":"2023-12-31","period_type":"Q","cash":200994000.0,"total_assets":5093312000.0,"long_term_debt":null,"total_liabilities":2743693000.0,"stockholders_equity":2343070000.0},{"period_end":"2024-03-31","period_type":"Q","cash":249355000.0,"total_assets":5129520000.0,"long_term_debt":1420625000.0,"total_liabilities":2750091000.0,"stockholders_equity":2370312000.0},{"period_end":"2024-06-30","period_type":"Q","cash":218317000.0,"total_assets":5118566000.0,"long_term_debt":1415938000.0,"total_liabilities":2746047000.0,"stockholders_equity":2372519000.0},{"period_end":"2024-09-30","period_type":"Q","cash":214177000.0,"total_assets":5186939000.0,"long_term_debt":1371875000.0,"total_liabilities":2774477000.0,"stockholders_equity":2412462000.0},{"period_end":"2024-12-31","period_type":"A","cash":281277000.0,"total_assets":5109331000.0,"long_term_debt":1211250000.0,"total_liabilities":2611888000.0,"stockholders_equity":2494278000.0},{"period_end":"2024-12-31","period_type":"Q","cash":281277000.0,"total_assets":5109331000.0,"long_term_debt":null,"total_liabilities":2611888000.0,"stockholders_equity":2494278000.0},{"period_end":"2025-03-31","period_type":"Q","cash":187464000.0,"total_assets":5060454000.0,"long_term_debt":null,"total_liabilities":2587429000.0,"stockholders_equity":2473025000.0},{"period_end":"2025-06-30","period_type":"Q","cash":223531000.0,"total_assets":5388801000.0,"long_term_debt":1280000000.0,"total_liabilities":2813610000.0,"stockholders_equity":2575191000.0},{"period_end":"2025-09-30","period_type":"Q","cash":300009000.0,"total_assets":5598102000.0,"long_term_debt":1285000000.0,"total_liabilities":2948274000.0,"stockholders_equity":2643748000.0},{"period_end":"2025-12-31","period_type":"A","cash":341413000.0,"total_assets":5573679000.0,"long_term_debt":1193750000.0,"total_liabilities":2934633000.0,"stockholders_equity":2632422000.0}],"cash_flows":[{"period_end":"2009-12-31","period_type":"A","operating_cf":74607000.0,"capex":4525000.0,"dividends_paid":null,"free_cash_flow":70082000.0},{"period_end":"2010-06-30","period_type":"Q","operating_cf":46645000.0,"capex":3035000.0,"dividends_paid":null,"free_cash_flow":43610000.0},{"period_end":"2010-09-30","period_type":"Q","operating_cf":83121000.0,"capex":4324000.0,"dividends_paid":null,"free_cash_flow":78797000.0},{"period_end":"2010-12-31","period_type":"A","operating_cf":114481000.0,"capex":9631000.0,"dividends_paid":0.0,"free_cash_flow":104850000.0},{"period_end":"2011-03-31","period_type":"Q","operating_cf":12671000.0,"capex":1569000.0,"dividends_paid":null,"free_cash_flow":11102000.0},{"period_end":"2011-06-30","period_type":"Q","operating_cf":27984000.0,"capex":3404000.0,"dividends_paid":0.0,"free_cash_flow":24580000.0},{"period_end":"2011-09-30","period_type":"Q","operating_cf":89015000.0,"capex":4461000.0,"dividends_paid":null,"free_cash_flow":84554000.0},{"period_end":"2011-12-31","period_type":"A","operating_cf":169712000.0,"capex":12060000.0,"dividends_paid":0.0,"free_cash_flow":157652000.0},{"period_end":"2012-03-31","period_type":"Q","operating_cf":38584000.0,"capex":2138000.0,"dividends_paid":0.0,"free_cash_flow":36446000.0},{"period_end":"2012-06-30","period_type":"Q","operating_cf":59707000.0,"capex":5504000.0,"dividends_paid":404332000.0,"free_cash_flow":54203000.0},{"period_end":"2012-09-30","period_type":"Q","operating_cf":129224000.0,"capex":13425000.0,"dividends_paid":404332000.0,"free_cash_flow":115799000.0},{"period_end":"2012-12-31","period_type":"A","operating_cf":235594000.0,"capex":22392000.0,"dividends_paid":404332000.0,"free_cash_flow":213202000.0},{"period_end":"2013-03-31","period_type":"Q","operating_cf":38266000.0,"capex":4322000.0,"dividends_paid":2649000.0,"free_cash_flow":33944000.0},{"period_end":"2013-06-30","period_type":"Q","operating_cf":74318000.0,"capex":10051000.0,"dividends_paid":343421000.0,"free_cash_flow":64267000.0},{"period_end":"2013-09-30","period_type":"Q","operating_cf":155213000.0,"capex":14257000.0,"dividends_paid":343424000.0,"free_cash_flow":140956000.0},{"period_end":"2013-12-31","period_type":"A","operating_cf":259944000.0,"capex":30770000.0,"dividends_paid":343429000.0,"free_cash_flow":229174000.0},{"period_end":"2014-03-31","period_type":"Q","operating_cf":36353000.0,"capex":4925000.0,"dividends_paid":334000.0,"free_cash_flow":31428000.0},{"period_end":"2014-06-30","period_type":"Q","operating_cf":85285000.0,"capex":13317000.0,"dividends_paid":459000.0,"free_cash_flow":71968000.0},{"period_end":"2014-09-30","period_type":"Q","operating_cf":142511000.0,"capex":22722000.0,"dividends_paid":705000.0,"free_cash_flow":119789000.0},{"period_end":"2014-12-31","period_type":"A","operating_cf":252986000.0,"capex":34689000.0,"dividends_paid":902000.0,"free_cash_flow":218297000.0},{"period_end":"2015-03-31","period_type":"Q","operating_cf":25257000.0,"capex":6528000.0,"dividends_paid":1427000.0,"free_cash_flow":18729000.0},{"period_end":"2015-06-30","period_type":"Q","operating_cf":41579000.0,"capex":14258000.0,"dividends_paid":1427000.0,"free_cash_flow":27321000.0},{"period_end":"2015-09-30","period_type":"Q","operating_cf":76859000.0,"capex":20108000.0,"dividends_paid":1429000.0,"free_cash_flow":56751000.0},{"period_end":"2015-12-31","period_type":"A","operating_cf":188619000.0,"capex":30651000.0,"dividends_paid":1436000.0,"free_cash_flow":157968000.0},{"period_end":"2016-03-31","period_type":"Q","operating_cf":22151000.0,"capex":7093000.0,"dividends_paid":76000.0,"free_cash_flow":15058000.0},{"period_end":"2016-06-30","period_type":"Q","operating_cf":81235000.0,"capex":14004000.0,"dividends_paid":76000.0,"free_cash_flow":67231000.0},{"period_end":"2016-09-30","period_type":"Q","operating_cf":129513000.0,"capex":20847000.0,"dividends_paid":76000.0,"free_cash_flow":108666000.0},{"period_end":"2016-12-31","period_type":"A","operating_cf":241122000.0,"capex":30467000.0,"dividends_paid":76000.0,"free_cash_flow":210655000.0},{"period_end":"2017-03-31","period_type":"Q","operating_cf":-5175000.0,"capex":3548000.0,"dividends_paid":null,"free_cash_flow":-8723000.0},{"period_end":"2017-06-30","period_type":"Q","operating_cf":54276000.0,"capex":10030000.0,"dividends_paid":null,"free_cash_flow":44246000.0},{"period_end":"2017-09-30","period_type":"Q","operating_cf":120617000.0,"capex":16658000.0,"dividends_paid":null,"free_cash_flow":103959000.0},{"period_end":"2017-12-31","period_type":"A","operating_cf":257322000.0,"capex":33261000.0,"dividends_paid":0.0,"free_cash_flow":224061000.0},{"period_end":"2018-03-31","period_type":"Q","operating_cf":28968000.0,"capex":6496000.0,"dividends_paid":314000.0,"free_cash_flow":22472000.0},{"period_end":"2018-06-30","period_type":"Q","operating_cf":79657000.0,"capex":12326000.0,"dividends_paid":314000.0,"free_cash_flow":67331000.0},{"period_end":"2018-09-30","period_type":"Q","operating_cf":138998000.0,"capex":25577000.0,"dividends_paid":314000.0,"free_cash_flow":113421000.0},{"period_end":"2018-12-31","period_type":"A","operating_cf":247227000.0,"capex":47601000.0,"dividends_paid":314000.0,"free_cash_flow":199626000.0},{"period_end":"2019-03-31","period_type":"Q","operating_cf":14571000.0,"capex":15902000.0,"dividends_paid":null,"free_cash_flow":-1331000.0},{"period_end":"2019-06-30","period_type":"Q","operating_cf":22614000.0,"capex":34376000.0,"dividends_paid":285000.0,"free_cash_flow":-11762000.0},{"period_end":"2019-09-30","period_type":"Q","operating_cf":133802000.0,"capex":45447000.0,"dividends_paid":285000.0,"free_cash_flow":88355000.0},{"period_end":"2019-12-31","period_type":"A","operating_cf":308887000.0,"capex":60802000.0,"dividends_paid":285000.0,"free_cash_flow":248085000.0},{"period_end":"2020-03-31","period_type":"Q","operating_cf":11346000.0,"capex":12894000.0,"dividends_paid":null,"free_cash_flow":-1548000.0},{"period_end":"2020-06-30","period_type":"Q","operating_cf":113114000.0,"capex":26332000.0,"dividends_paid":0.0,"free_cash_flow":86782000.0},{"period_end":"2020-09-30","period_type":"Q","operating_cf":268310000.0,"capex":33940000.0,"dividends_paid":0.0,"free_cash_flow":234370000.0},{"period_end":"2020-12-31","period_type":"A","operating_cf":486533000.0,"capex":62128000.0,"dividends_paid":0.0,"free_cash_flow":424405000.0},{"period_end":"2021-03-31","period_type":"Q","operating_cf":152543000.0,"capex":27469000.0,"dividends_paid":null,"free_cash_flow":125074000.0},{"period_end":"2021-06-30","period_type":"Q","operating_cf":274993000.0,"capex":54222000.0,"dividends_paid":null,"free_cash_flow":220771000.0},{"period_end":"2021-09-30","period_type":"Q","operating_cf":349404000.0,"capex":87456000.0,"dividends_paid":0.0,"free_cash_flow":261948000.0},{"period_end":"2021-12-31","period_type":"A","operating_cf":411156000.0,"capex":109992000.0,"dividends_paid":0.0,"free_cash_flow":301164000.0},{"period_end":"2022-03-31","period_type":"Q","operating_cf":-10142000.0,"capex":28200000.0,"dividends_paid":null,"free_cash_flow":-38342000.0},{"period_end":"2022-06-30","period_type":"Q","operating_cf":13693000.0,"capex":46503000.0,"dividends_paid":null,"free_cash_flow":-32810000.0},{"period_end":"2022-09-30","period_type":"Q","operating_cf":-42352000.0,"capex":64833000.0,"dividends_paid":309000.0,"free_cash_flow":-107185000.0},{"period_end":"2022-12-31","period_type":"A","operating_cf":58516000.0,"capex":86188000.0,"dividends_paid":309000.0,"free_cash_flow":-27672000.0},{"period_end":"2023-03-31","period_type":"Q","operating_cf":-18559000.0,"capex":23977000.0,"dividends_paid":null,"free_cash_flow":-42536000.0},{"period_end":"2023-06-30","period_type":"Q","operating_cf":64588000.0,"capex":53900000.0,"dividends_paid":null,"free_cash_flow":10688000.0},{"period_end":"2023-09-30","period_type":"Q","operating_cf":204724000.0,"capex":77718000.0,"dividends_paid":null,"free_cash_flow":127006000.0},{"period_end":"2023-12-31","period_type":"A","operating_cf":521670000.0,"capex":129060000.0,"dividends_paid":0.0,"free_cash_flow":392610000.0},{"period_end":"2024-03-31","period_type":"Q","operating_cf":111898000.0,"capex":26820000.0,"dividends_paid":null,"free_cash_flow":85078000.0},{"period_end":"2024-06-30","period_type":"Q","operating_cf":189562000.0,"capex":54772000.0,"dividends_paid":0.0,"free_cash_flow":134790000.0},{"period_end":"2024-09-30","period_type":"Q","operating_cf":401847000.0,"capex":83399000.0,"dividends_paid":0.0,"free_cash_flow":318448000.0},{"period_end":"2024-12-31","period_type":"A","operating_cf":741301000.0,"capex":136733000.0,"dividends_paid":273000.0,"free_cash_flow":604568000.0},{"period_end":"2025-03-31","period_type":"Q","operating_cf":58152000.0,"capex":30937000.0,"dividends_paid":null,"free_cash_flow":27215000.0},{"period_end":"2025-06-30","period_type":"Q","operating_cf":130341000.0,"capex":88653000.0,"dividends_paid":293000.0,"free_cash_flow":41688000.0},{"period_end":"2025-09-30","period_type":"Q","operating_cf":248719000.0,"capex":110534000.0,"dividends_paid":293000.0,"free_cash_flow":138185000.0},{"period_end":"2025-12-31","period_type":"A","operating_cf":437978000.0,"capex":169850000.0,"dividends_paid":293000.0,"free_cash_flow":268128000.0}],"earnings_surprises":[{"earnings_date":"2020-04-30","eps_estimate":0.8,"eps_actual":0.87,"eps_surprise_pct":8.3},{"earnings_date":"2020-07-30","eps_estimate":0.89,"eps_actual":1.4,"eps_surprise_pct":57.82},{"earnings_date":"2020-10-28","eps_estimate":1.71,"eps_actual":2.08,"eps_surprise_pct":21.61},{"earnings_date":"2021-02-11","eps_estimate":1.96,"eps_actual":2.12,"eps_surprise_pct":8.13},{"earnings_date":"2021-04-29","eps_estimate":1.88,"eps_actual":2.38,"eps_surprise_pct":26.54},{"earnings_date":"2021-07-28","eps_estimate":2.32,"eps_actual":2.39,"eps_surprise_pct":3.03},{"earnings_date":"2021-11-02","eps_estimate":2.39,"eps_actual":2.35,"eps_surprise_pct":-1.56},{"earnings_date":"2022-02-16","eps_estimate":2.4,"eps_actual":2.51,"eps_surprise_pct":4.71},{"earnings_date":"2022-05-04","eps_estimate":1.92,"eps_actual":2.09,"eps_surprise_pct":8.62},{"earnings_date":"2022-08-03","eps_estimate":2.64,"eps_actual":2.99,"eps_surprise_pct":13.37},{"earnings_date":"2022-11-02","eps_estimate":1.82,"eps_actual":1.75,"eps_surprise_pct":-3.73},{"earnings_date":"2023-02-15","eps_estimate":1.75,"eps_actual":1.78,"eps_surprise_pct":1.49},{"earnings_date":"2023-05-03","eps_estimate":0.5,"eps_actual":0.63,"eps_surprise_pct":25.79},{"earnings_date":"2023-08-02","eps_estimate":1.18,"eps_actual":1.08,"eps_surprise_pct":-8.12},{"earnings_date":"2023-11-01","eps_estimate":1.51,"eps_actual":1.64,"eps_surprise_pct":8.37},{"earnings_date":"2024-02-14","eps_estimate":2.09,"eps_actual":2.07,"eps_surprise_pct":-0.92},{"earnings_date":"2024-05-01","eps_estimate":0.71,"eps_actual":0.88,"eps_surprise_pct":23.96},{"earnings_date":"2024-07-31","eps_estimate":1.2,"eps_actual":1.35,"eps_surprise_pct":12.34},{"earnings_date":"2024-10-31","eps_estimate":1.95,"eps_actual":2.25,"eps_surprise_pct":15.48},{"earnings_date":"2025-02-12","eps_estimate":2.53,"eps_actual":2.8,"eps_surprise_pct":10.82},{"earnings_date":"2025-04-30","eps_estimate":0.97,"eps_actual":1.26,"eps_surprise_pct":30.39},{"earnings_date":"2025-07-30","eps_estimate":1.32,"eps_actual":1.65,"eps_surprise_pct":24.58},{"earnings_date":"2025-10-29","eps_estimate":2.2,"eps_actual":1.83,"eps_surprise_pct":-16.72},{"earnings_date":"2026-02-11","eps_estimate":1.77,"eps_actual":1.61,"eps_surprise_pct":-9.02},{"earnings_date":"2026-04-29","eps_estimate":1.3,"eps_actual":null,"eps_surprise_pct":null}],"valuation_snapshots":[]}