{"income_statements":[{"period_end":"2008-12-31","period_type":"A","fiscal_year":2010,"fiscal_quarter":null,"revenue":2054800000.0,"gross_profit":745500000.0,"operating_income":-365900000.0,"net_income":-428900000.0,"eps_diluted":-1.13},{"period_end":"2009-07-03","period_type":"Q","fiscal_year":2010,"fiscal_quarter":2,"revenue":798900000.0,"gross_profit":250300000.0,"operating_income":9100000.0,"net_income":-36900000.0,"eps_diluted":-0.09},{"period_end":"2009-10-02","period_type":"Q","fiscal_year":2010,"fiscal_quarter":3,"revenue":1271800000.0,"gross_profit":426100000.0,"operating_income":58800000.0,"net_income":-7000000.0,"eps_diluted":-0.02},{"period_end":"2009-12-31","period_type":"A","fiscal_year":2011,"fiscal_quarter":null,"revenue":1768900000.0,"gross_profit":620700000.0,"operating_income":142600000.0,"net_income":61000000.0,"eps_diluted":0.14},{"period_end":"2010-04-02","period_type":"A","fiscal_year":2011,"fiscal_quarter":null,"revenue":550200000.0,"gross_profit":228100000.0,"operating_income":null,"net_income":63000000.0,"eps_diluted":0.14},{"period_end":"2010-04-02","period_type":"Q","fiscal_year":2011,"fiscal_quarter":1,"revenue":550200000.0,"gross_profit":228100000.0,"operating_income":84200000.0,"net_income":63000000.0,"eps_diluted":0.14},{"period_end":"2010-07-02","period_type":"A","fiscal_year":2011,"fiscal_quarter":null,"revenue":583300000.0,"gross_profit":243800000.0,"operating_income":null,"net_income":78700000.0,"eps_diluted":0.18},{"period_end":"2010-07-02","period_type":"Q","fiscal_year":2011,"fiscal_quarter":2,"revenue":1133500000.0,"gross_profit":471900000.0,"operating_income":185700000.0,"net_income":141700000.0,"eps_diluted":0.32},{"period_end":"2010-10-01","period_type":"A","fiscal_year":2011,"fiscal_quarter":null,"revenue":600700000.0,"gross_profit":246500000.0,"operating_income":null,"net_income":87800000.0,"eps_diluted":0.2},{"period_end":"2010-10-01","period_type":"Q","fiscal_year":2011,"fiscal_quarter":3,"revenue":1734200000.0,"gross_profit":718400000.0,"operating_income":293400000.0,"net_income":229500000.0,"eps_diluted":0.52},{"period_end":"2010-12-31","period_type":"A","fiscal_year":2012,"fiscal_quarter":null,"revenue":2313400000.0,"gross_profit":956000000.0,"operating_income":374200000.0,"net_income":290500000.0,"eps_diluted":0.65},{"period_end":"2011-03-31","period_type":"A","fiscal_year":2012,"fiscal_quarter":null,"revenue":870600000.0,"gross_profit":242400000.0,"operating_income":null,"net_income":35500000.0,"eps_diluted":0.08},{"period_end":"2011-04-01","period_type":"A","fiscal_year":2011,"fiscal_quarter":null,"revenue":870600000.0,"gross_profit":242400000.0,"operating_income":null,"net_income":35500000.0,"eps_diluted":0.08},{"period_end":"2011-04-01","period_type":"Q","fiscal_year":2012,"fiscal_quarter":1,"revenue":870600000.0,"gross_profit":242400000.0,"operating_income":32700000.0,"net_income":35500000.0,"eps_diluted":0.08},{"period_end":"2011-06-30","period_type":"A","fiscal_year":2012,"fiscal_quarter":null,"revenue":905800000.0,"gross_profit":266100000.0,"operating_income":null,"net_income":34300000.0,"eps_diluted":0.07},{"period_end":"2011-07-01","period_type":"A","fiscal_year":2011,"fiscal_quarter":null,"revenue":905800000.0,"gross_profit":266100000.0,"operating_income":null,"net_income":34300000.0,"eps_diluted":0.07},{"period_end":"2011-07-01","period_type":"Q","fiscal_year":2012,"fiscal_quarter":2,"revenue":1776400000.0,"gross_profit":508500000.0,"operating_income":89600000.0,"net_income":69800000.0,"eps_diluted":0.15},{"period_end":"2011-09-30","period_type":"A","fiscal_year":2012,"fiscal_quarter":null,"revenue":898000000.0,"gross_profit":261100000.0,"operating_income":null,"net_income":-49400000.0,"eps_diluted":-0.11},{"period_end":"2011-09-30","period_type":"Q","fiscal_year":2012,"fiscal_quarter":3,"revenue":2674400000.0,"gross_profit":769600000.0,"operating_income":82900000.0,"net_income":20400000.0,"eps_diluted":0.04},{"period_end":"2011-12-31","period_type":"A","fiscal_year":2013,"fiscal_quarter":null,"revenue":3442300000.0,"gross_profit":1008800000.0,"operating_income":113400000.0,"net_income":11600000.0,"eps_diluted":0.03},{"period_end":"2012-03-30","period_type":"A","fiscal_year":2013,"fiscal_quarter":null,"revenue":744400000.0,"gross_profit":245200000.0,"operating_income":null,"net_income":28200000.0,"eps_diluted":0.06},{"period_end":"2012-03-30","period_type":"Q","fiscal_year":2013,"fiscal_quarter":1,"revenue":744400000.0,"gross_profit":245200000.0,"operating_income":43600000.0,"net_income":28200000.0,"eps_diluted":0.06},{"period_end":"2012-03-31","period_type":"A","fiscal_year":2012,"fiscal_quarter":null,"revenue":744400000.0,"gross_profit":245200000.0,"operating_income":null,"net_income":28200000.0,"eps_diluted":0.06},{"period_end":"2012-06-29","period_type":"A","fiscal_year":2013,"fiscal_quarter":null,"revenue":744800000.0,"gross_profit":258300000.0,"operating_income":null,"net_income":6900000.0,"eps_diluted":0.02},{"period_end":"2012-06-29","period_type":"Q","fiscal_year":2013,"fiscal_quarter":2,"revenue":1489200000.0,"gross_profit":503500000.0,"operating_income":70500000.0,"net_income":35100000.0,"eps_diluted":0.08},{"period_end":"2012-06-30","period_type":"A","fiscal_year":2012,"fiscal_quarter":null,"revenue":744800000.0,"gross_profit":258300000.0,"operating_income":null,"net_income":6900000.0,"eps_diluted":0.02},{"period_end":"2012-09-28","period_type":"A","fiscal_year":2013,"fiscal_quarter":null,"revenue":725500000.0,"gross_profit":238000000.0,"operating_income":null,"net_income":12500000.0,"eps_diluted":0.03},{"period_end":"2012-09-28","period_type":"Q","fiscal_year":2013,"fiscal_quarter":3,"revenue":2214700000.0,"gross_profit":741500000.0,"operating_income":115100000.0,"net_income":47600000.0,"eps_diluted":0.1},{"period_end":"2012-09-30","period_type":"A","fiscal_year":2012,"fiscal_quarter":null,"revenue":725500000.0,"gross_profit":238000000.0,"operating_income":null,"net_income":12500000.0,"eps_diluted":0.03},{"period_end":"2012-12-31","period_type":"A","fiscal_year":2014,"fiscal_quarter":null,"revenue":2894900000.0,"gross_profit":946300000.0,"operating_income":-20300000.0,"net_income":-97200000.0,"eps_diluted":-0.21},{"period_end":"2013-03-29","period_type":"A","fiscal_year":2014,"fiscal_quarter":null,"revenue":661000000.0,"gross_profit":197600000.0,"operating_income":null,"net_income":16100000.0,"eps_diluted":0.04},{"period_end":"2013-03-29","period_type":"Q","fiscal_year":2014,"fiscal_quarter":1,"revenue":661000000.0,"gross_profit":204500000.0,"operating_income":37700000.0,"net_income":22600000.0,"eps_diluted":0.05},{"period_end":"2013-06-28","period_type":"A","fiscal_year":2014,"fiscal_quarter":null,"revenue":688300000.0,"gross_profit":231900000.0,"operating_income":null,"net_income":45800000.0,"eps_diluted":0.1},{"period_end":"2013-06-28","period_type":"Q","fiscal_year":2014,"fiscal_quarter":2,"revenue":1349300000.0,"gross_profit":436300000.0,"operating_income":88600000.0,"net_income":70300000.0,"eps_diluted":0.16},{"period_end":"2013-09-27","period_type":"A","fiscal_year":2014,"fiscal_quarter":null,"revenue":715400000.0,"gross_profit":249200000.0,"operating_income":null,"net_income":50700000.0,"eps_diluted":0.11},{"period_end":"2013-09-27","period_type":"Q","fiscal_year":2014,"fiscal_quarter":3,"revenue":2064700000.0,"gross_profit":685500000.0,"operating_income":155900000.0,"net_income":122100000.0,"eps_diluted":0.27},{"period_end":"2013-12-31","period_type":"A","fiscal_year":2015,"fiscal_quarter":null,"revenue":2782700000.0,"gross_profit":929100000.0,"operating_income":208900000.0,"net_income":150400000.0,"eps_diluted":0.33},{"period_end":"2014-03-28","period_type":"A","fiscal_year":2015,"fiscal_quarter":null,"revenue":706500000.0,"gross_profit":248200000.0,"operating_income":null,"net_income":55700000.0,"eps_diluted":0.13},{"period_end":"2014-03-28","period_type":"Q","fiscal_year":2015,"fiscal_quarter":1,"revenue":706500000.0,"gross_profit":248200000.0,"operating_income":70700000.0,"net_income":55700000.0,"eps_diluted":0.13},{"period_end":"2014-06-27","period_type":"A","fiscal_year":2015,"fiscal_quarter":null,"revenue":757600000.0,"gross_profit":278100000.0,"operating_income":null,"net_income":94100000.0,"eps_diluted":0.21},{"period_end":"2014-06-27","period_type":"Q","fiscal_year":2015,"fiscal_quarter":2,"revenue":1464100000.0,"gross_profit":526300000.0,"operating_income":157500000.0,"net_income":149800000.0,"eps_diluted":0.34},{"period_end":"2014-09-26","period_type":"A","fiscal_year":2015,"fiscal_quarter":null,"revenue":833500000.0,"gross_profit":280900000.0,"operating_income":null,"net_income":40500000.0,"eps_diluted":0.09},{"period_end":"2014-09-26","period_type":"Q","fiscal_year":2015,"fiscal_quarter":3,"revenue":2297600000.0,"gross_profit":807200000.0,"operating_income":214300000.0,"net_income":190300000.0,"eps_diluted":0.43},{"period_end":"2014-12-31","period_type":"A","fiscal_year":2016,"fiscal_quarter":null,"revenue":3161800000.0,"gross_profit":1084900000.0,"operating_income":228900000.0,"net_income":189700000.0,"eps_diluted":0.43},{"period_end":"2015-04-03","period_type":"A","fiscal_year":2016,"fiscal_quarter":null,"revenue":870800000.0,"gross_profit":300400000.0,"operating_income":null,"net_income":55100000.0,"eps_diluted":0.13},{"period_end":"2015-04-03","period_type":"Q","fiscal_year":2016,"fiscal_quarter":1,"revenue":870800000.0,"gross_profit":300400000.0,"operating_income":68400000.0,"net_income":55100000.0,"eps_diluted":0.13},{"period_end":"2015-07-03","period_type":"A","fiscal_year":2016,"fiscal_quarter":null,"revenue":880500000.0,"gross_profit":304400000.0,"operating_income":null,"net_income":50700000.0,"eps_diluted":0.12},{"period_end":"2015-07-03","period_type":"Q","fiscal_year":2016,"fiscal_quarter":2,"revenue":1751300000.0,"gross_profit":604800000.0,"operating_income":136200000.0,"net_income":105800000.0,"eps_diluted":0.24},{"period_end":"2015-10-02","period_type":"A","fiscal_year":2016,"fiscal_quarter":null,"revenue":904200000.0,"gross_profit":308500000.0,"operating_income":null,"net_income":46300000.0,"eps_diluted":0.11},{"period_end":"2015-10-02","period_type":"Q","fiscal_year":2016,"fiscal_quarter":3,"revenue":2655500000.0,"gross_profit":913300000.0,"operating_income":205600000.0,"net_income":152100000.0,"eps_diluted":0.35},{"period_end":"2015-12-31","period_type":"A","fiscal_year":2017,"fiscal_quarter":null,"revenue":3495800000.0,"gross_profit":1193200000.0,"operating_income":261100000.0,"net_income":206200000.0,"eps_diluted":0.48},{"period_end":"2016-04-01","period_type":"A","fiscal_year":2017,"fiscal_quarter":null,"revenue":817200000.0,"gross_profit":275500000.0,"operating_income":null,"net_income":36000000.0,"eps_diluted":0.09},{"period_end":"2016-04-01","period_type":"Q","fiscal_year":2017,"fiscal_quarter":1,"revenue":817200000.0,"gross_profit":275500000.0,"operating_income":58400000.0,"net_income":36000000.0,"eps_diluted":0.09},{"period_end":"2016-07-01","period_type":"A","fiscal_year":2017,"fiscal_quarter":null,"revenue":877800000.0,"gross_profit":307900000.0,"operating_income":null,"net_income":25100000.0,"eps_diluted":0.06},{"period_end":"2016-07-01","period_type":"Q","fiscal_year":2017,"fiscal_quarter":2,"revenue":1695000000.0,"gross_profit":583400000.0,"operating_income":133700000.0,"net_income":61100000.0,"eps_diluted":0.15},{"period_end":"2016-09-30","period_type":"A","fiscal_year":2017,"fiscal_quarter":null,"revenue":950900000.0,"gross_profit":329000000.0,"operating_income":null,"net_income":10100000.0,"eps_diluted":0.02},{"period_end":"2016-09-30","period_type":"Q","fiscal_year":2017,"fiscal_quarter":3,"revenue":2645900000.0,"gross_profit":912400000.0,"operating_income":180400000.0,"net_income":71200000.0,"eps_diluted":0.17},{"period_end":"2016-12-31","period_type":"A","fiscal_year":2018,"fiscal_quarter":null,"revenue":3906900000.0,"gross_profit":1300500000.0,"operating_income":246800000.0,"net_income":182100000.0,"eps_diluted":0.43},{"period_end":"2017-03-31","period_type":"A","fiscal_year":2018,"fiscal_quarter":null,"revenue":1436700000.0,"gross_profit":503100000.0,"operating_income":null,"net_income":78200000.0,"eps_diluted":0.18},{"period_end":"2017-03-31","period_type":"Q","fiscal_year":2018,"fiscal_quarter":1,"revenue":1436700000.0,"gross_profit":503100000.0,"operating_income":183100000.0,"net_income":78200000.0,"eps_diluted":0.18},{"period_end":"2017-06-30","period_type":"A","fiscal_year":2018,"fiscal_quarter":null,"revenue":1338000000.0,"gross_profit":492000000.0,"operating_income":null,"net_income":93900000.0,"eps_diluted":0.22},{"period_end":"2017-06-30","period_type":"Q","fiscal_year":2018,"fiscal_quarter":2,"revenue":2774700000.0,"gross_profit":995100000.0,"operating_income":337100000.0,"net_income":172100000.0,"eps_diluted":0.4},{"period_end":"2017-09-29","period_type":"A","fiscal_year":2018,"fiscal_quarter":null,"revenue":1390900000.0,"gross_profit":524000000.0,"operating_income":null,"net_income":108700000.0,"eps_diluted":0.25},{"period_end":"2017-09-29","period_type":"Q","fiscal_year":2018,"fiscal_quarter":3,"revenue":4165600000.0,"gross_profit":1519100000.0,"operating_income":514100000.0,"net_income":280800000.0,"eps_diluted":0.66},{"period_end":"2017-12-31","period_type":"A","fiscal_year":2019,"fiscal_quarter":null,"revenue":5543100000.0,"gross_profit":2035600000.0,"operating_income":681600000.0,"net_income":810700000.0,"eps_diluted":1.89},{"period_end":"2018-03-30","period_type":"A","fiscal_year":2019,"fiscal_quarter":null,"revenue":1377600000.0,"gross_profit":517400000.0,"operating_income":null,"net_income":139600000.0,"eps_diluted":0.31},{"period_end":"2018-03-30","period_type":"Q","fiscal_year":2019,"fiscal_quarter":1,"revenue":1377600000.0,"gross_profit":517400000.0,"operating_income":185700000.0,"net_income":139600000.0,"eps_diluted":0.31},{"period_end":"2018-06-29","period_type":"A","fiscal_year":2019,"fiscal_quarter":null,"revenue":1455900000.0,"gross_profit":555000000.0,"operating_income":null,"net_income":155300000.0,"eps_diluted":0.35},{"period_end":"2018-06-29","period_type":"Q","fiscal_year":2019,"fiscal_quarter":2,"revenue":2833500000.0,"gross_profit":1072400000.0,"operating_income":382900000.0,"net_income":294900000.0,"eps_diluted":0.66},{"period_end":"2018-09-28","period_type":"A","fiscal_year":2019,"fiscal_quarter":null,"revenue":1541700000.0,"gross_profit":596600000.0,"operating_income":null,"net_income":166900000.0,"eps_diluted":0.38},{"period_end":"2018-09-28","period_type":"Q","fiscal_year":2019,"fiscal_quarter":3,"revenue":4375200000.0,"gross_profit":1669000000.0,"operating_income":624500000.0,"net_income":461800000.0,"eps_diluted":1.05},{"period_end":"2018-12-31","period_type":"A","fiscal_year":2020,"fiscal_quarter":null,"revenue":5878300000.0,"gross_profit":2238700000.0,"operating_income":847200000.0,"net_income":627400000.0,"eps_diluted":1.44},{"period_end":"2019-03-29","period_type":"A","fiscal_year":2020,"fiscal_quarter":null,"revenue":1386600000.0,"gross_profit":513700000.0,"operating_income":null,"net_income":114100000.0,"eps_diluted":0.27},{"period_end":"2019-03-29","period_type":"Q","fiscal_year":2020,"fiscal_quarter":1,"revenue":1386600000.0,"gross_profit":513700000.0,"operating_income":179400000.0,"net_income":114100000.0,"eps_diluted":0.27},{"period_end":"2019-06-28","period_type":"A","fiscal_year":2020,"fiscal_quarter":null,"revenue":1347700000.0,"gross_profit":499000000.0,"operating_income":null,"net_income":101800000.0,"eps_diluted":0.24},{"period_end":"2019-06-28","period_type":"Q","fiscal_year":2020,"fiscal_quarter":2,"revenue":2734300000.0,"gross_profit":1012700000.0,"operating_income":337700000.0,"net_income":215900000.0,"eps_diluted":0.52},{"period_end":"2019-09-27","period_type":"A","fiscal_year":2020,"fiscal_quarter":null,"revenue":1381800000.0,"gross_profit":475200000.0,"operating_income":null,"net_income":-60700000.0,"eps_diluted":-0.15},{"period_end":"2019-09-27","period_type":"Q","fiscal_year":2020,"fiscal_quarter":3,"revenue":4116100000.0,"gross_profit":1487900000.0,"operating_income":293800000.0,"net_income":155200000.0,"eps_diluted":0.37},{"period_end":"2019-12-31","period_type":"A","fiscal_year":2021,"fiscal_quarter":null,"revenue":5517900000.0,"gross_profit":1973600000.0,"operating_income":432700000.0,"net_income":211700000.0,"eps_diluted":0.51},{"period_end":"2020-04-03","period_type":"A","fiscal_year":2020,"fiscal_quarter":null,"revenue":1277900000.0,"gross_profit":402700000.0,"operating_income":null,"net_income":-14000000.0,"eps_diluted":-0.03},{"period_end":"2020-04-03","period_type":"Q","fiscal_year":2021,"fiscal_quarter":1,"revenue":1277900000.0,"gross_profit":402700000.0,"operating_income":18600000.0,"net_income":-14000000.0,"eps_diluted":-0.03},{"period_end":"2020-07-03","period_type":"A","fiscal_year":2020,"fiscal_quarter":null,"revenue":1213500000.0,"gross_profit":374300000.0,"operating_income":null,"net_income":-1400000.0,"eps_diluted":0.0},{"period_end":"2020-07-03","period_type":"Q","fiscal_year":2021,"fiscal_quarter":2,"revenue":2491400000.0,"gross_profit":777000000.0,"operating_income":61700000.0,"net_income":-15400000.0,"eps_diluted":-0.04},{"period_end":"2020-10-02","period_type":"A","fiscal_year":2020,"fiscal_quarter":null,"revenue":1317300000.0,"gross_profit":441200000.0,"operating_income":null,"net_income":160600000.0,"eps_diluted":0.38},{"period_end":"2020-10-02","period_type":"Q","fiscal_year":2021,"fiscal_quarter":3,"revenue":3808700000.0,"gross_profit":1218200000.0,"operating_income":180700000.0,"net_income":145200000.0,"eps_diluted":0.35},{"period_end":"2020-12-31","period_type":"A","fiscal_year":2022,"fiscal_quarter":null,"revenue":5255000000.0,"gross_profit":1715800000.0,"operating_income":348700000.0,"net_income":234200000.0,"eps_diluted":0.56},{"period_end":"2021-04-02","period_type":"Q","fiscal_year":2022,"fiscal_quarter":1,"revenue":1481700000.0,"gross_profit":521200000.0,"operating_income":125900000.0,"net_income":89900000.0,"eps_diluted":0.2},{"period_end":"2021-07-02","period_type":"Q","fiscal_year":2022,"fiscal_quarter":2,"revenue":3151600000.0,"gross_profit":1161300000.0,"operating_income":408100000.0,"net_income":274000000.0,"eps_diluted":0.62},{"period_end":"2021-10-01","period_type":"Q","fiscal_year":2022,"fiscal_quarter":3,"revenue":4893700000.0,"gross_profit":1882100000.0,"operating_income":807300000.0,"net_income":583700000.0,"eps_diluted":1.32},{"period_end":"2021-12-31","period_type":"A","fiscal_year":2023,"fiscal_quarter":null,"revenue":6739800000.0,"gross_profit":2714300000.0,"operating_income":1287600000.0,"net_income":1009600000.0,"eps_diluted":2.27},{"period_end":"2022-04-01","period_type":"Q","fiscal_year":2023,"fiscal_quarter":1,"revenue":1945000000.0,"gross_profit":961300000.0,"operating_income":647200000.0,"net_income":530200000.0,"eps_diluted":1.18},{"period_end":"2022-07-01","period_type":"Q","fiscal_year":2023,"fiscal_quarter":2,"revenue":4030000000.0,"gross_profit":1998400000.0,"operating_income":1231200000.0,"net_income":986000000.0,"eps_diluted":2.2},{"period_end":"2022-09-30","period_type":"Q","fiscal_year":2023,"fiscal_quarter":3,"revenue":6222600000.0,"gross_profit":3056700000.0,"operating_income":1655700000.0,"net_income":1297900000.0,"eps_diluted":2.9},{"period_end":"2022-12-31","period_type":"A","fiscal_year":2024,"fiscal_quarter":null,"revenue":8326200000.0,"gross_profit":4077200000.0,"operating_income":2360000000.0,"net_income":1902200000.0,"eps_diluted":4.25},{"period_end":"2023-03-31","period_type":"Q","fiscal_year":2024,"fiscal_quarter":1,"revenue":1959700000.0,"gross_profit":917500000.0,"operating_income":564900000.0,"net_income":461700000.0,"eps_diluted":1.03},{"period_end":"2023-06-30","period_type":"Q","fiscal_year":2024,"fiscal_quarter":2,"revenue":4054100000.0,"gross_profit":1910900000.0,"operating_income":1239600000.0,"net_income":1038300000.0,"eps_diluted":2.32},{"period_end":"2023-09-29","period_type":"Q","fiscal_year":2024,"fiscal_quarter":3,"revenue":6234900000.0,"gross_profit":2941600000.0,"operating_income":1926600000.0,"net_income":1621000000.0,"eps_diluted":3.61},{"period_end":"2023-12-31","period_type":"A","fiscal_year":2025,"fiscal_quarter":null,"revenue":8253000000.0,"gross_profit":3883500000.0,"operating_income":2538700000.0,"net_income":2183700000.0,"eps_diluted":4.89},{"period_end":"2024-03-29","period_type":"Q","fiscal_year":2025,"fiscal_quarter":1,"revenue":1862700000.0,"gross_profit":853600000.0,"operating_income":525200000.0,"net_income":453000000.0,"eps_diluted":1.04},{"period_end":"2024-06-28","period_type":"Q","fiscal_year":2025,"fiscal_quarter":2,"revenue":3597900000.0,"gross_profit":1637600000.0,"operating_income":913700000.0,"net_income":791200000.0,"eps_diluted":1.82},{"period_end":"2024-09-27","period_type":"Q","fiscal_year":2025,"fiscal_quarter":3,"revenue":5359800000.0,"gross_profit":2437000000.0,"operating_income":1359100000.0,"net_income":1192900000.0,"eps_diluted":2.75},{"period_end":"2024-12-31","period_type":"A","fiscal_year":2025,"fiscal_quarter":null,"revenue":7082300000.0,"gross_profit":3216100000.0,"operating_income":1767700000.0,"net_income":1572800000.0,"eps_diluted":3.63},{"period_end":"2025-04-04","period_type":"Q","fiscal_year":2025,"fiscal_quarter":1,"revenue":1445700000.0,"gross_profit":293800000.0,"operating_income":-573700000.0,"net_income":-486100000.0,"eps_diluted":-1.15},{"period_end":"2025-07-04","period_type":"Q","fiscal_year":2025,"fiscal_quarter":2,"revenue":2914400000.0,"gross_profit":845700000.0,"operating_income":-380300000.0,"net_income":-315800000.0,"eps_diluted":-0.76},{"period_end":"2025-10-03","period_type":"Q","fiscal_year":2025,"fiscal_quarter":3,"revenue":4465300000.0,"gross_profit":1432900000.0,"operating_income":-115900000.0,"net_income":-60800000.0,"eps_diluted":-0.15},{"period_end":"2025-12-31","period_type":"A","fiscal_year":2025,"fiscal_quarter":null,"revenue":5995400000.0,"gross_profit":1983900000.0,"operating_income":84200000.0,"net_income":121000000.0,"eps_diluted":0.29}],"balance_sheets":[{"period_end":"2007-12-31","period_type":"A","cash":274600000.0,"total_assets":null,"long_term_debt":null,"total_liabilities":null,"stockholders_equity":242700000.0},{"period_end":"2008-12-31","period_type":"A","cash":458700000.0,"total_assets":null,"long_term_debt":null,"total_liabilities":null,"stockholders_equity":855500000.0},{"period_end":"2008-12-31","period_type":"Q","cash":458700000.0,"total_assets":null,"long_term_debt":null,"total_liabilities":null,"stockholders_equity":null},{"period_end":"2009-07-03","period_type":"Q","cash":403400000.0,"total_assets":null,"long_term_debt":null,"total_liabilities":null,"stockholders_equity":null},{"period_end":"2009-10-02","period_type":"Q","cash":395200000.0,"total_assets":null,"long_term_debt":null,"total_liabilities":null,"stockholders_equity":null},{"period_end":"2009-12-31","period_type":"A","cash":525700000.0,"total_assets":2414300000.0,"long_term_debt":727600000.0,"total_liabilities":1409700000.0,"stockholders_equity":1004600000.0},{"period_end":"2009-12-31","period_type":"Q","cash":525700000.0,"total_assets":2414300000.0,"long_term_debt":727600000.0,"total_liabilities":1409700000.0,"stockholders_equity":985000000.0},{"period_end":"2010-04-02","period_type":"Q","cash":560700000.0,"total_assets":null,"long_term_debt":null,"total_liabilities":null,"stockholders_equity":null},{"period_end":"2010-07-02","period_type":"Q","cash":467100000.0,"total_assets":2541000000.0,"long_term_debt":632900000.0,"total_liabilities":1341700000.0,"stockholders_equity":1178100000.0},{"period_end":"2010-10-01","period_type":"Q","cash":562900000.0,"total_assets":2694500000.0,"long_term_debt":650200000.0,"total_liabilities":1391900000.0,"stockholders_equity":1280800000.0},{"period_end":"2010-12-31","period_type":"A","cash":623300000.0,"total_assets":2919200000.0,"long_term_debt":888800000.0,"total_liabilities":1531200000.0,"stockholders_equity":1388000000.0},{"period_end":"2010-12-31","period_type":"Q","cash":623300000.0,"total_assets":2919200000.0,"long_term_debt":888800000.0,"total_liabilities":1531200000.0,"stockholders_equity":1366000000.0},{"period_end":"2011-04-01","period_type":"Q","cash":766000000.0,"total_assets":4016800000.0,"long_term_debt":1095200000.0,"total_liabilities":2507100000.0,"stockholders_equity":1487000000.0},{"period_end":"2011-07-01","period_type":"Q","cash":659300000.0,"total_assets":4149800000.0,"long_term_debt":1285400000.0,"total_liabilities":2562200000.0,"stockholders_equity":1564100000.0},{"period_end":"2011-09-30","period_type":"Q","cash":659300000.0,"total_assets":4011900000.0,"long_term_debt":1237000000.0,"total_liabilities":2486200000.0,"stockholders_equity":1501800000.0},{"period_end":"2011-12-31","period_type":"A","cash":652900000.0,"total_assets":3883500000.0,"long_term_debt":1207000000.0,"total_liabilities":2390000000.0,"stockholders_equity":1537300000.0},{"period_end":"2011-12-31","period_type":"Q","cash":652900000.0,"total_assets":3883500000.0,"long_term_debt":1207000000.0,"total_liabilities":2390000000.0,"stockholders_equity":1468200000.0},{"period_end":"2012-03-30","period_type":"Q","cash":580100000.0,"total_assets":3829200000.0,"long_term_debt":1189000000.0,"total_liabilities":2294700000.0,"stockholders_equity":1508400000.0},{"period_end":"2012-03-31","period_type":"A","cash":580100000.0,"total_assets":null,"long_term_debt":null,"total_liabilities":null,"stockholders_equity":null},{"period_end":"2012-06-29","period_type":"Q","cash":517800000.0,"total_assets":3770700000.0,"long_term_debt":1070300000.0,"total_liabilities":2226100000.0,"stockholders_equity":1517200000.0},{"period_end":"2012-06-30","period_type":"A","cash":517800000.0,"total_assets":null,"long_term_debt":null,"total_liabilities":null,"stockholders_equity":null},{"period_end":"2012-09-28","period_type":"Q","cash":421400000.0,"total_assets":3669900000.0,"long_term_debt":1063400000.0,"total_liabilities":2130300000.0,"stockholders_equity":1511300000.0},{"period_end":"2012-09-30","period_type":"A","cash":421400000.0,"total_assets":null,"long_term_debt":null,"total_liabilities":null,"stockholders_equity":null},{"period_end":"2012-12-31","period_type":"A","cash":486900000.0,"total_assets":3328400000.0,"long_term_debt":1011900000.0,"total_liabilities":1937700000.0,"stockholders_equity":1427900000.0},{"period_end":"2012-12-31","period_type":"Q","cash":486900000.0,"total_assets":3328400000.0,"long_term_debt":1011900000.0,"total_liabilities":1937700000.0,"stockholders_equity":1361100000.0},{"period_end":"2013-03-29","period_type":"Q","cash":537000000.0,"total_assets":3232700000.0,"long_term_debt":949600000.0,"total_liabilities":1818800000.0,"stockholders_equity":1383600000.0},{"period_end":"2013-06-28","period_type":"Q","cash":396100000.0,"total_assets":3241400000.0,"long_term_debt":917600000.0,"total_liabilities":1776100000.0,"stockholders_equity":1434000000.0},{"period_end":"2013-09-27","period_type":"Q","cash":369500000.0,"total_assets":3248700000.0,"long_term_debt":908400000.0,"total_liabilities":1747000000.0,"stockholders_equity":1469400000.0},{"period_end":"2013-12-31","period_type":"A","cash":509500000.0,"total_assets":3293800000.0,"long_term_debt":942200000.0,"total_liabilities":1770200000.0,"stockholders_equity":1523600000.0},{"period_end":"2013-12-31","period_type":"Q","cash":509500000.0,"total_assets":3257000000.0,"long_term_debt":942200000.0,"total_liabilities":1770200000.0,"stockholders_equity":1454000000.0},{"period_end":"2014-03-28","period_type":"Q","cash":562000000.0,"total_assets":3286700000.0,"long_term_debt":920200000.0,"total_liabilities":1746800000.0,"stockholders_equity":1506900000.0},{"period_end":"2014-06-27","period_type":"Q","cash":598900000.0,"total_assets":3418400000.0,"long_term_debt":904900000.0,"total_liabilities":1778900000.0,"stockholders_equity":1606700000.0},{"period_end":"2014-09-26","period_type":"Q","cash":492100000.0,"total_assets":3882200000.0,"long_term_debt":1183600000.0,"total_liabilities":2207900000.0,"stockholders_equity":1642600000.0},{"period_end":"2014-12-31","period_type":"A","cash":511700000.0,"total_assets":3822100000.0,"long_term_debt":1207300000.0,"total_liabilities":2174700000.0,"stockholders_equity":1647400000.0},{"period_end":"2014-12-31","period_type":"Q","cash":511700000.0,"total_assets":3823000000.0,"long_term_debt":983000000.0,"total_liabilities":2175600000.0,"stockholders_equity":1626500000.0},{"period_end":"2015-04-03","period_type":"Q","cash":428100000.0,"total_assets":3746300000.0,"long_term_debt":1162800000.0,"total_liabilities":2119100000.0,"stockholders_equity":1605600000.0},{"period_end":"2015-07-03","period_type":"Q","cash":576600000.0,"total_assets":3915400000.0,"long_term_debt":1378200000.0,"total_liabilities":2295700000.0,"stockholders_equity":1597400000.0},{"period_end":"2015-10-02","period_type":"Q","cash":556800000.0,"total_assets":3950100000.0,"long_term_debt":1521600000.0,"total_liabilities":2369000000.0,"stockholders_equity":1558300000.0},{"period_end":"2015-12-31","period_type":"A","cash":617600000.0,"total_assets":3869600000.0,"long_term_debt":850500000.0,"total_liabilities":2237700000.0,"stockholders_equity":1631900000.0},{"period_end":"2015-12-31","period_type":"Q","cash":617600000.0,"total_assets":3869600000.0,"long_term_debt":1515800000.0,"total_liabilities":2237700000.0,"stockholders_equity":1608200000.0},{"period_end":"2016-04-01","period_type":"Q","cash":619500000.0,"total_assets":3855100000.0,"long_term_debt":1475200000.0,"total_liabilities":2177000000.0,"stockholders_equity":1654000000.0},{"period_end":"2016-07-01","period_type":"Q","cash":588100000.0,"total_assets":6097800000.0,"long_term_debt":3652200000.0,"total_liabilities":4372100000.0,"stockholders_equity":1700900000.0},{"period_end":"2016-09-30","period_type":"Q","cash":880500000.0,"total_assets":6790900000.0,"long_term_debt":3831300000.0,"total_liabilities":5036900000.0,"stockholders_equity":1730600000.0},{"period_end":"2016-12-31","period_type":"A","cash":1028100000.0,"total_assets":6924400000.0,"long_term_debt":3068500000.0,"total_liabilities":5046500000.0,"stockholders_equity":1845000000.0},{"period_end":"2016-12-31","period_type":"Q","cash":1028100000.0,"total_assets":6924400000.0,"long_term_debt":3068500000.0,"total_liabilities":5046500000.0,"stockholders_equity":1823200000.0},{"period_end":"2017-03-31","period_type":"Q","cash":728900000.0,"total_assets":6637400000.0,"long_term_debt":3538400000.0,"total_liabilities":4639100000.0,"stockholders_equity":1976000000.0},{"period_end":"2017-06-30","period_type":"Q","cash":871600000.0,"total_assets":6834300000.0,"long_term_debt":3407300000.0,"total_liabilities":4715000000.0,"stockholders_equity":2096500000.0},{"period_end":"2017-09-29","period_type":"Q","cash":901200000.0,"total_assets":6861300000.0,"long_term_debt":3191100000.0,"total_liabilities":4625900000.0,"stockholders_equity":2212400000.0},{"period_end":"2017-12-31","period_type":"A","cash":949200000.0,"total_assets":7195100000.0,"long_term_debt":2703700000.0,"total_liabilities":4394100000.0,"stockholders_equity":2801000000.0},{"period_end":"2017-12-31","period_type":"Q","cash":949200000.0,"total_assets":7195100000.0,"long_term_debt":2703700000.0,"total_liabilities":4394100000.0,"stockholders_equity":2801000000.0},{"period_end":"2018-03-30","period_type":"Q","cash":924900000.0,"total_assets":7263100000.0,"long_term_debt":3043500000.0,"total_liabilities":4311600000.0,"stockholders_equity":2951500000.0},{"period_end":"2018-06-29","period_type":"Q","cash":850200000.0,"total_assets":7297300000.0,"long_term_debt":2964100000.0,"total_liabilities":4200500000.0,"stockholders_equity":3096800000.0},{"period_end":"2018-09-28","period_type":"Q","cash":951000000.0,"total_assets":7409800000.0,"long_term_debt":2900100000.0,"total_liabilities":4206400000.0,"stockholders_equity":3203400000.0},{"period_end":"2018-12-31","period_type":"A","cash":1069600000.0,"total_assets":7587600000.0,"long_term_debt":2627600000.0,"total_liabilities":4393500000.0,"stockholders_equity":3194100000.0},{"period_end":"2018-12-31","period_type":"Q","cash":1069600000.0,"total_assets":7587600000.0,"long_term_debt":2627600000.0,"total_liabilities":4393500000.0,"stockholders_equity":3194100000.0},{"period_end":"2019-03-29","period_type":"Q","cash":939600000.0,"total_assets":7564300000.0,"long_term_debt":2931100000.0,"total_liabilities":4343600000.0,"stockholders_equity":3220700000.0},{"period_end":"2019-06-28","period_type":"Q","cash":885200000.0,"total_assets":8524500000.0,"long_term_debt":3805800000.0,"total_liabilities":5226600000.0,"stockholders_equity":3297900000.0},{"period_end":"2019-09-27","period_type":"Q","cash":928700000.0,"total_assets":8522300000.0,"long_term_debt":3764600000.0,"total_liabilities":5282700000.0,"stockholders_equity":3239600000.0},{"period_end":"2019-12-31","period_type":"A","cash":894200000.0,"total_assets":8425500000.0,"long_term_debt":2876500000.0,"total_liabilities":5101400000.0,"stockholders_equity":3324100000.0},{"period_end":"2019-12-31","period_type":"Q","cash":894200000.0,"total_assets":8425500000.0,"long_term_debt":2876500000.0,"total_liabilities":5101400000.0,"stockholders_equity":3324100000.0},{"period_end":"2020-04-03","period_type":"Q","cash":1982000000.0,"total_assets":9420800000.0,"long_term_debt":4857500000.0,"total_liabilities":6183200000.0,"stockholders_equity":3237600000.0},{"period_end":"2020-07-03","period_type":"Q","cash":2060400000.0,"total_assets":9527800000.0,"long_term_debt":4853200000.0,"total_liabilities":6268500000.0,"stockholders_equity":3259300000.0},{"period_end":"2020-10-02","period_type":"Q","cash":1654000000.0,"total_assets":9254000000.0,"long_term_debt":4348800000.0,"total_liabilities":5806800000.0,"stockholders_equity":3447200000.0},{"period_end":"2020-12-31","period_type":"A","cash":1080700000.0,"total_assets":8668000000.0,"long_term_debt":2959700000.0,"total_liabilities":5109900000.0,"stockholders_equity":3558100000.0},{"period_end":"2020-12-31","period_type":"Q","cash":1080700000.0,"total_assets":8668000000.0,"long_term_debt":2959700000.0,"total_liabilities":5109900000.0,"stockholders_equity":3558100000.0},{"period_end":"2021-04-02","period_type":"Q","cash":1042500000.0,"total_assets":8630400000.0,"long_term_debt":3435400000.0,"total_liabilities":4980800000.0,"stockholders_equity":3649600000.0},{"period_end":"2021-07-02","period_type":"Q","cash":1091100000.0,"total_assets":8594400000.0,"long_term_debt":3313900000.0,"total_liabilities":4790000000.0,"stockholders_equity":3804400000.0},{"period_end":"2021-10-01","period_type":"Q","cash":1389200000.0,"total_assets":8940700000.0,"long_term_debt":3309900000.0,"total_liabilities":4796300000.0,"stockholders_equity":4144400000.0},{"period_end":"2021-12-31","period_type":"A","cash":1352600000.0,"total_assets":9626000000.0,"long_term_debt":2913900000.0,"total_liabilities":5021600000.0,"stockholders_equity":4604400000.0},{"period_end":"2021-12-31","period_type":"Q","cash":1352600000.0,"total_assets":9626000000.0,"long_term_debt":2913900000.0,"total_liabilities":5021600000.0,"stockholders_equity":4604400000.0},{"period_end":"2022-04-01","period_type":"Q","cash":1645100000.0,"total_assets":10212400000.0,"long_term_debt":3254200000.0,"total_liabilities":5194400000.0,"stockholders_equity":5018000000.0},{"period_end":"2022-07-01","period_type":"Q","cash":1791600000.0,"total_assets":10788700000.0,"long_term_debt":3251500000.0,"total_liabilities":5378600000.0,"stockholders_equity":5410100000.0},{"period_end":"2022-09-30","period_type":"Q","cash":2450200000.0,"total_assets":11100700000.0,"long_term_debt":3248800000.0,"total_liabilities":5424100000.0,"stockholders_equity":5676600000.0},{"period_end":"2022-12-31","period_type":"A","cash":2919000000.0,"total_assets":11978500000.0,"long_term_debt":3045700000.0,"total_liabilities":5771500000.0,"stockholders_equity":6207000000.0},{"period_end":"2022-12-31","period_type":"Q","cash":2919000000.0,"total_assets":11978500000.0,"long_term_debt":3045700000.0,"total_liabilities":5771500000.0,"stockholders_equity":6207000000.0},{"period_end":"2023-03-31","period_type":"Q","cash":2702400000.0,"total_assets":12274300000.0,"long_term_debt":3514600000.0,"total_liabilities":5807300000.0,"stockholders_equity":6467000000.0},{"period_end":"2023-06-30","period_type":"Q","cash":2622200000.0,"total_assets":12762700000.0,"long_term_debt":3499600000.0,"total_liabilities":5759100000.0,"stockholders_equity":7003600000.0},{"period_end":"2023-09-29","period_type":"Q","cash":2679200000.0,"total_assets":13281300000.0,"long_term_debt":3499500000.0,"total_liabilities":5777300000.0,"stockholders_equity":7504000000.0},{"period_end":"2023-12-31","period_type":"A","cash":2483000000.0,"total_assets":13215200000.0,"long_term_debt":2542600000.0,"total_liabilities":5414600000.0,"stockholders_equity":7800600000.0},{"period_end":"2023-12-31","period_type":"Q","cash":2483000000.0,"total_assets":13215200000.0,"long_term_debt":2542600000.0,"total_liabilities":5414600000.0,"stockholders_equity":7800600000.0},{"period_end":"2024-03-29","period_type":"Q","cash":2614400000.0,"total_assets":13482900000.0,"long_term_debt":3379900000.0,"total_liabilities":5340300000.0,"stockholders_equity":8142600000.0},{"period_end":"2024-06-28","period_type":"Q","cash":2231000000.0,"total_assets":13658800000.0,"long_term_debt":3379900000.0,"total_liabilities":5300400000.0,"stockholders_equity":8358400000.0},{"period_end":"2024-09-27","period_type":"Q","cash":2470200000.0,"total_assets":13923600000.0,"long_term_debt":3379900000.0,"total_liabilities":5319600000.0,"stockholders_equity":8604000000.0},{"period_end":"2024-12-31","period_type":"A","cash":2691300000.0,"total_assets":14089800000.0,"long_term_debt":3345900000.0,"total_liabilities":5275300000.0,"stockholders_equity":8796400000.0},{"period_end":"2024-12-31","period_type":"Q","cash":2691300000.0,"total_assets":14089800000.0,"long_term_debt":3345900000.0,"total_liabilities":5275300000.0,"stockholders_equity":8796400000.0},{"period_end":"2025-04-04","period_type":"Q","cash":2762500000.0,"total_assets":13253900000.0,"long_term_debt":3379900000.0,"total_liabilities":5205000000.0,"stockholders_equity":8048900000.0},{"period_end":"2025-07-04","period_type":"Q","cash":2526700000.0,"total_assets":13126200000.0,"long_term_debt":3379900000.0,"total_liabilities":5165000000.0,"stockholders_equity":7961200000.0},{"period_end":"2025-10-03","period_type":"Q","cash":2472500000.0,"total_assets":13010200000.0,"long_term_debt":3379900000.0,"total_liabilities":5084100000.0,"stockholders_equity":7905400000.0},{"period_end":"2025-12-31","period_type":"A","cash":2147600000.0,"total_assets":12524100000.0,"long_term_debt":2980500000.0,"total_liabilities":4832200000.0,"stockholders_equity":7673300000.0}],"cash_flows":[{"period_end":"2008-12-31","period_type":"A","operating_cf":393800000.0,"capex":95000000.0,"dividends_paid":null,"free_cash_flow":298800000.0},{"period_end":"2009-07-03","period_type":"Q","operating_cf":87000000.0,"capex":37000000.0,"dividends_paid":null,"free_cash_flow":50000000.0},{"period_end":"2009-10-02","period_type":"Q","operating_cf":174600000.0,"capex":46300000.0,"dividends_paid":null,"free_cash_flow":128300000.0},{"period_end":"2009-12-31","period_type":"A","operating_cf":279300000.0,"capex":55300000.0,"dividends_paid":null,"free_cash_flow":224000000.0},{"period_end":"2010-04-02","period_type":"Q","operating_cf":109500000.0,"capex":41000000.0,"dividends_paid":null,"free_cash_flow":68500000.0},{"period_end":"2010-07-02","period_type":"Q","operating_cf":268400000.0,"capex":93500000.0,"dividends_paid":null,"free_cash_flow":174900000.0},{"period_end":"2010-10-01","period_type":"Q","operating_cf":392000000.0,"capex":145900000.0,"dividends_paid":null,"free_cash_flow":246100000.0},{"period_end":"2010-12-31","period_type":"A","operating_cf":551800000.0,"capex":188900000.0,"dividends_paid":null,"free_cash_flow":362900000.0},{"period_end":"2011-04-01","period_type":"Q","operating_cf":125600000.0,"capex":88700000.0,"dividends_paid":null,"free_cash_flow":36900000.0},{"period_end":"2011-07-01","period_type":"Q","operating_cf":261600000.0,"capex":173500000.0,"dividends_paid":null,"free_cash_flow":88100000.0},{"period_end":"2011-09-30","period_type":"Q","operating_cf":380800000.0,"capex":259300000.0,"dividends_paid":null,"free_cash_flow":121500000.0},{"period_end":"2011-12-31","period_type":"A","operating_cf":545500000.0,"capex":316400000.0,"dividends_paid":null,"free_cash_flow":229100000.0},{"period_end":"2012-03-30","period_type":"Q","operating_cf":68400000.0,"capex":50400000.0,"dividends_paid":null,"free_cash_flow":18000000.0},{"period_end":"2012-03-31","period_type":"A","operating_cf":68400000.0,"capex":50400000.0,"dividends_paid":null,"free_cash_flow":18000000.0},{"period_end":"2012-06-29","period_type":"Q","operating_cf":127500000.0,"capex":114700000.0,"dividends_paid":null,"free_cash_flow":12800000.0},{"period_end":"2012-06-30","period_type":"A","operating_cf":127500000.0,"capex":114700000.0,"dividends_paid":null,"free_cash_flow":12800000.0},{"period_end":"2012-09-28","period_type":"Q","operating_cf":139400000.0,"capex":198800000.0,"dividends_paid":null,"free_cash_flow":-59400000.0},{"period_end":"2012-09-30","period_type":"A","operating_cf":139400000.0,"capex":198800000.0,"dividends_paid":null,"free_cash_flow":-59400000.0},{"period_end":"2012-12-31","period_type":"A","operating_cf":276000000.0,"capex":256300000.0,"dividends_paid":null,"free_cash_flow":19700000.0},{"period_end":"2013-03-29","period_type":"Q","operating_cf":85200000.0,"capex":38900000.0,"dividends_paid":null,"free_cash_flow":46300000.0},{"period_end":"2013-06-28","period_type":"Q","operating_cf":140400000.0,"capex":84700000.0,"dividends_paid":null,"free_cash_flow":55700000.0},{"period_end":"2013-09-27","period_type":"Q","operating_cf":200300000.0,"capex":135100000.0,"dividends_paid":null,"free_cash_flow":65200000.0},{"period_end":"2013-12-31","period_type":"A","operating_cf":327300000.0,"capex":155200000.0,"dividends_paid":null,"free_cash_flow":172100000.0},{"period_end":"2014-03-28","period_type":"Q","operating_cf":74900000.0,"capex":47700000.0,"dividends_paid":null,"free_cash_flow":27200000.0},{"period_end":"2014-06-27","period_type":"Q","operating_cf":226500000.0,"capex":96500000.0,"dividends_paid":null,"free_cash_flow":130000000.0},{"period_end":"2014-09-26","period_type":"Q","operating_cf":318800000.0,"capex":163000000.0,"dividends_paid":null,"free_cash_flow":155800000.0},{"period_end":"2014-12-31","period_type":"A","operating_cf":481300000.0,"capex":204300000.0,"dividends_paid":null,"free_cash_flow":277000000.0},{"period_end":"2015-04-03","period_type":"Q","operating_cf":83500000.0,"capex":64800000.0,"dividends_paid":null,"free_cash_flow":18700000.0},{"period_end":"2015-07-03","period_type":"Q","operating_cf":185100000.0,"capex":140300000.0,"dividends_paid":null,"free_cash_flow":44800000.0},{"period_end":"2015-10-02","period_type":"Q","operating_cf":313400000.0,"capex":204800000.0,"dividends_paid":null,"free_cash_flow":108600000.0},{"period_end":"2015-12-31","period_type":"A","operating_cf":470600000.0,"capex":270800000.0,"dividends_paid":null,"free_cash_flow":199800000.0},{"period_end":"2016-04-01","period_type":"Q","operating_cf":114900000.0,"capex":72900000.0,"dividends_paid":null,"free_cash_flow":42000000.0},{"period_end":"2016-07-01","period_type":"Q","operating_cf":219100000.0,"capex":124900000.0,"dividends_paid":null,"free_cash_flow":94200000.0},{"period_end":"2016-09-30","period_type":"Q","operating_cf":351800000.0,"capex":160800000.0,"dividends_paid":null,"free_cash_flow":191000000.0},{"period_end":"2016-12-31","period_type":"A","operating_cf":581100000.0,"capex":210700000.0,"dividends_paid":null,"free_cash_flow":370400000.0},{"period_end":"2017-03-31","period_type":"Q","operating_cf":208500000.0,"capex":52700000.0,"dividends_paid":null,"free_cash_flow":155800000.0},{"period_end":"2017-06-30","period_type":"Q","operating_cf":541700000.0,"capex":121700000.0,"dividends_paid":null,"free_cash_flow":420000000.0},{"period_end":"2017-09-29","period_type":"Q","operating_cf":869900000.0,"capex":211800000.0,"dividends_paid":null,"free_cash_flow":658100000.0},{"period_end":"2017-12-31","period_type":"A","operating_cf":1094200000.0,"capex":387500000.0,"dividends_paid":null,"free_cash_flow":706700000.0},{"period_end":"2018-03-30","period_type":"Q","operating_cf":226500000.0,"capex":99500000.0,"dividends_paid":null,"free_cash_flow":127000000.0},{"period_end":"2018-06-29","period_type":"Q","operating_cf":495000000.0,"capex":252400000.0,"dividends_paid":null,"free_cash_flow":242600000.0},{"period_end":"2018-09-28","period_type":"Q","operating_cf":853200000.0,"capex":382800000.0,"dividends_paid":null,"free_cash_flow":470400000.0},{"period_end":"2018-12-31","period_type":"A","operating_cf":1274200000.0,"capex":514800000.0,"dividends_paid":null,"free_cash_flow":759400000.0},{"period_end":"2019-03-29","period_type":"Q","operating_cf":138200000.0,"capex":157000000.0,"dividends_paid":null,"free_cash_flow":-18800000.0},{"period_end":"2019-06-28","period_type":"Q","operating_cf":360800000.0,"capex":310500000.0,"dividends_paid":null,"free_cash_flow":50300000.0},{"period_end":"2019-09-27","period_type":"Q","operating_cf":603000000.0,"capex":422200000.0,"dividends_paid":null,"free_cash_flow":180800000.0},{"period_end":"2019-12-31","period_type":"A","operating_cf":694700000.0,"capex":534600000.0,"dividends_paid":null,"free_cash_flow":160100000.0},{"period_end":"2020-04-03","period_type":"Q","operating_cf":166000000.0,"capex":132300000.0,"dividends_paid":null,"free_cash_flow":33700000.0},{"period_end":"2020-07-03","period_type":"Q","operating_cf":320500000.0,"capex":205600000.0,"dividends_paid":null,"free_cash_flow":114900000.0},{"period_end":"2020-10-02","period_type":"Q","operating_cf":483900000.0,"capex":267200000.0,"dividends_paid":null,"free_cash_flow":216700000.0},{"period_end":"2020-12-31","period_type":"A","operating_cf":884300000.0,"capex":383600000.0,"dividends_paid":null,"free_cash_flow":500700000.0},{"period_end":"2021-04-02","period_type":"Q","operating_cf":218500000.0,"capex":77000000.0,"dividends_paid":null,"free_cash_flow":141500000.0},{"period_end":"2021-07-02","period_type":"Q","operating_cf":706500000.0,"capex":181800000.0,"dividends_paid":null,"free_cash_flow":524700000.0},{"period_end":"2021-10-01","period_type":"Q","operating_cf":1155400000.0,"capex":275000000.0,"dividends_paid":null,"free_cash_flow":880400000.0},{"period_end":"2021-12-31","period_type":"A","operating_cf":1782000000.0,"capex":444600000.0,"dividends_paid":null,"free_cash_flow":1337400000.0},{"period_end":"2022-04-01","period_type":"Q","operating_cf":478600000.0,"capex":173800000.0,"dividends_paid":null,"free_cash_flow":304800000.0},{"period_end":"2022-07-01","period_type":"Q","operating_cf":899400000.0,"capex":391900000.0,"dividends_paid":null,"free_cash_flow":507500000.0},{"period_end":"2022-09-30","period_type":"Q","operating_cf":1901800000.0,"capex":663000000.0,"dividends_paid":null,"free_cash_flow":1238800000.0},{"period_end":"2022-12-31","period_type":"A","operating_cf":2633100000.0,"capex":1036000000.0,"dividends_paid":null,"free_cash_flow":1597100000.0},{"period_end":"2023-03-31","period_type":"Q","operating_cf":408900000.0,"capex":321500000.0,"dividends_paid":null,"free_cash_flow":87400000.0},{"period_end":"2023-06-30","period_type":"Q","operating_cf":799700000.0,"capex":752100000.0,"dividends_paid":null,"free_cash_flow":47600000.0},{"period_end":"2023-09-29","period_type":"Q","operating_cf":1366300000.0,"capex":1185100000.0,"dividends_paid":null,"free_cash_flow":181200000.0},{"period_end":"2023-12-31","period_type":"A","operating_cf":1977500000.0,"capex":1539100000.0,"dividends_paid":null,"free_cash_flow":438400000.0},{"period_end":"2024-03-29","period_type":"Q","operating_cf":498700000.0,"capex":233900000.0,"dividends_paid":null,"free_cash_flow":264800000.0},{"period_end":"2024-06-28","period_type":"Q","operating_cf":860900000.0,"capex":375000000.0,"dividends_paid":null,"free_cash_flow":485900000.0},{"period_end":"2024-09-27","period_type":"Q","operating_cf":1326700000.0,"capex":536700000.0,"dividends_paid":null,"free_cash_flow":790000000.0},{"period_end":"2024-12-31","period_type":"A","operating_cf":1906400000.0,"capex":694000000.0,"dividends_paid":null,"free_cash_flow":1212400000.0},{"period_end":"2025-04-04","period_type":"Q","operating_cf":602300000.0,"capex":147600000.0,"dividends_paid":null,"free_cash_flow":454700000.0},{"period_end":"2025-07-04","period_type":"Q","operating_cf":786600000.0,"capex":225800000.0,"dividends_paid":null,"free_cash_flow":560800000.0},{"period_end":"2025-10-03","period_type":"Q","operating_cf":1205300000.0,"capex":272100000.0,"dividends_paid":null,"free_cash_flow":933200000.0},{"period_end":"2025-12-31","period_type":"A","operating_cf":1759800000.0,"capex":341200000.0,"dividends_paid":null,"free_cash_flow":1418600000.0}],"earnings_surprises":[{"earnings_date":"2020-05-09","eps_estimate":0.15,"eps_actual":0.1,"eps_surprise_pct":-34.27},{"earnings_date":"2020-08-08","eps_estimate":0.02,"eps_actual":0.12,"eps_surprise_pct":544.81},{"earnings_date":"2020-10-31","eps_estimate":0.2,"eps_actual":0.27,"eps_surprise_pct":34.25},{"earnings_date":"2021-02-01","eps_estimate":0.28,"eps_actual":0.35,"eps_surprise_pct":26.11},{"earnings_date":"2021-05-03","eps_estimate":0.34,"eps_actual":0.35,"eps_surprise_pct":4.46},{"earnings_date":"2021-08-02","eps_estimate":0.49,"eps_actual":0.63,"eps_surprise_pct":28.76},{"earnings_date":"2021-11-01","eps_estimate":0.74,"eps_actual":0.87,"eps_surprise_pct":18.25},{"earnings_date":"2022-02-07","eps_estimate":0.94,"eps_actual":1.09,"eps_surprise_pct":15.98},{"earnings_date":"2022-05-02","eps_estimate":1.05,"eps_actual":1.22,"eps_surprise_pct":16.33},{"earnings_date":"2022-08-01","eps_estimate":1.26,"eps_actual":1.34,"eps_surprise_pct":6.32},{"earnings_date":"2022-10-31","eps_estimate":1.31,"eps_actual":1.45,"eps_surprise_pct":10.44},{"earnings_date":"2023-02-06","eps_estimate":1.26,"eps_actual":1.32,"eps_surprise_pct":4.41},{"earnings_date":"2023-05-01","eps_estimate":1.08,"eps_actual":1.19,"eps_surprise_pct":9.75},{"earnings_date":"2023-07-31","eps_estimate":1.21,"eps_actual":1.33,"eps_surprise_pct":9.82},{"earnings_date":"2023-10-30","eps_estimate":1.34,"eps_actual":1.39,"eps_surprise_pct":3.45},{"earnings_date":"2024-02-05","eps_estimate":1.2,"eps_actual":1.25,"eps_surprise_pct":4.01},{"earnings_date":"2024-04-29","eps_estimate":1.05,"eps_actual":1.08,"eps_surprise_pct":3.31},{"earnings_date":"2024-07-29","eps_estimate":0.92,"eps_actual":0.96,"eps_surprise_pct":4.58},{"earnings_date":"2024-10-28","eps_estimate":0.97,"eps_actual":0.99,"eps_surprise_pct":2.44},{"earnings_date":"2025-02-10","eps_estimate":0.97,"eps_actual":0.95,"eps_surprise_pct":-2.44},{"earnings_date":"2025-05-05","eps_estimate":0.5,"eps_actual":0.55,"eps_surprise_pct":9.59},{"earnings_date":"2025-08-04","eps_estimate":0.53,"eps_actual":0.53,"eps_surprise_pct":-0.39},{"earnings_date":"2025-11-03","eps_estimate":0.54,"eps_actual":0.63,"eps_surprise_pct":17.58},{"earnings_date":"2026-02-09","eps_estimate":0.59,"eps_actual":0.45,"eps_surprise_pct":-24.31},{"earnings_date":"2026-05-04","eps_estimate":0.61,"eps_actual":null,"eps_surprise_pct":null}],"valuation_snapshots":[]}