{"income_statements":[{"period_end":"2007-09-30","period_type":"A","fiscal_year":2009,"fiscal_quarter":null,"revenue":9411500000.0,"gross_profit":null,"operating_income":1053900000.0,"net_income":672600000.0,"eps_diluted":0.87},{"period_end":"2008-06-29","period_type":"Q","fiscal_year":2009,"fiscal_quarter":3,"revenue":7867600000.0,"gross_profit":null,"operating_income":489700000.0,"net_income":310100000.0,"eps_diluted":0.42},{"period_end":"2008-09-28","period_type":"A","fiscal_year":2010,"fiscal_quarter":null,"revenue":10383000000.0,"gross_profit":null,"operating_income":503900000.0,"net_income":315500000.0,"eps_diluted":0.43},{"period_end":"2008-12-28","period_type":"Q","fiscal_year":2010,"fiscal_quarter":1,"revenue":2615200000.0,"gross_profit":null,"operating_income":117700000.0,"net_income":64300000.0,"eps_diluted":0.09},{"period_end":"2009-03-29","period_type":"Q","fiscal_year":2010,"fiscal_quarter":2,"revenue":4948500000.0,"gross_profit":null,"operating_income":158600000.0,"net_income":89300000.0,"eps_diluted":0.12},{"period_end":"2009-06-28","period_type":"Q","fiscal_year":2010,"fiscal_quarter":3,"revenue":7352400000.0,"gross_profit":null,"operating_income":362600000.0,"net_income":240800000.0,"eps_diluted":0.32},{"period_end":"2009-09-27","period_type":"A","fiscal_year":2011,"fiscal_quarter":null,"revenue":9774600000.0,"gross_profit":null,"operating_income":562000000.0,"net_income":390800000.0,"eps_diluted":0.52},{"period_end":"2009-12-27","period_type":"Q","fiscal_year":2011,"fiscal_quarter":1,"revenue":2722700000.0,"gross_profit":null,"operating_income":352600000.0,"net_income":241500000.0,"eps_diluted":0.32},{"period_end":"2010-03-28","period_type":"Q","fiscal_year":2011,"fiscal_quarter":2,"revenue":5257400000.0,"gross_profit":null,"operating_income":692400000.0,"net_income":458800000.0,"eps_diluted":0.6},{"period_end":"2010-06-27","period_type":"Q","fiscal_year":2011,"fiscal_quarter":3,"revenue":7869400000.0,"gross_profit":null,"operating_income":1020100000.0,"net_income":666700000.0,"eps_diluted":0.87},{"period_end":"2010-10-03","period_type":"A","fiscal_year":2012,"fiscal_quarter":null,"revenue":10707400000.0,"gross_profit":null,"operating_income":1419400000.0,"net_income":945600000.0,"eps_diluted":1.24},{"period_end":"2011-01-02","period_type":"Q","fiscal_year":2012,"fiscal_quarter":1,"revenue":2950800000.0,"gross_profit":null,"operating_income":501900000.0,"net_income":346600000.0,"eps_diluted":0.45},{"period_end":"2011-04-03","period_type":"Q","fiscal_year":2012,"fiscal_quarter":2,"revenue":5736500000.0,"gross_profit":null,"operating_income":878000000.0,"net_income":608100000.0,"eps_diluted":0.79},{"period_end":"2011-07-03","period_type":"Q","fiscal_year":2012,"fiscal_quarter":3,"revenue":8668700000.0,"gross_profit":null,"operating_income":1280300000.0,"net_income":887400000.0,"eps_diluted":1.15},{"period_end":"2011-10-02","period_type":"A","fiscal_year":2013,"fiscal_quarter":null,"revenue":11700400000.0,"gross_profit":null,"operating_income":1728500000.0,"net_income":1245700000.0,"eps_diluted":1.62},{"period_end":"2012-01-01","period_type":"Q","fiscal_year":2013,"fiscal_quarter":1,"revenue":3435900000.0,"gross_profit":null,"operating_income":556000000.0,"net_income":382100000.0,"eps_diluted":0.5},{"period_end":"2012-04-01","period_type":"Q","fiscal_year":2013,"fiscal_quarter":2,"revenue":6631800000.0,"gross_profit":null,"operating_income":986400000.0,"net_income":691900000.0,"eps_diluted":0.9},{"period_end":"2012-07-01","period_type":"Q","fiscal_year":2013,"fiscal_quarter":3,"revenue":9935400000.0,"gross_profit":null,"operating_income":1477900000.0,"net_income":1025100000.0,"eps_diluted":1.33},{"period_end":"2012-09-30","period_type":"A","fiscal_year":2014,"fiscal_quarter":null,"revenue":13276800000.0,"gross_profit":null,"operating_income":1997400000.0,"net_income":1383800000.0,"eps_diluted":1.79},{"period_end":"2012-09-30","period_type":"Q","fiscal_year":2014,"fiscal_quarter":3,"revenue":13276800000.0,"gross_profit":null,"operating_income":1997400000.0,"net_income":1383800000.0,"eps_diluted":null},{"period_end":"2012-12-30","period_type":"A","fiscal_year":2014,"fiscal_quarter":null,"revenue":3793200000.0,"gross_profit":null,"operating_income":630600000.0,"net_income":432200000.0,"eps_diluted":0.57},{"period_end":"2012-12-30","period_type":"Q","fiscal_year":2014,"fiscal_quarter":3,"revenue":3793200000.0,"gross_profit":null,"operating_income":630600000.0,"net_income":432200000.0,"eps_diluted":0.57},{"period_end":"2013-03-31","period_type":"A","fiscal_year":2014,"fiscal_quarter":null,"revenue":3549600000.0,"gross_profit":null,"operating_income":544100000.0,"net_income":390400000.0,"eps_diluted":0.51},{"period_end":"2013-03-31","period_type":"Q","fiscal_year":2014,"fiscal_quarter":3,"revenue":3549600000.0,"gross_profit":null,"operating_income":544100000.0,"net_income":390400000.0,"eps_diluted":1.08},{"period_end":"2013-06-30","period_type":"A","fiscal_year":2014,"fiscal_quarter":null,"revenue":3735300000.0,"gross_profit":null,"operating_income":615200000.0,"net_income":417800000.0,"eps_diluted":0.55},{"period_end":"2013-06-30","period_type":"Q","fiscal_year":2014,"fiscal_quarter":3,"revenue":11078100000.0,"gross_profit":null,"operating_income":1789900000.0,"net_income":1240300000.0,"eps_diluted":1.63},{"period_end":"2013-09-29","period_type":"A","fiscal_year":2015,"fiscal_quarter":null,"revenue":14866800000.0,"gross_profit":null,"operating_income":-325400000.0,"net_income":8300000.0,"eps_diluted":0.01},{"period_end":"2013-09-29","period_type":"Q","fiscal_year":2014,"fiscal_quarter":3,"revenue":14866800000.0,"gross_profit":null,"operating_income":-325400000.0,"net_income":8300000.0,"eps_diluted":null},{"period_end":"2013-12-29","period_type":"A","fiscal_year":2015,"fiscal_quarter":null,"revenue":4239600000.0,"gross_profit":null,"operating_income":813500000.0,"net_income":540700000.0,"eps_diluted":0.35},{"period_end":"2013-12-29","period_type":"Q","fiscal_year":2015,"fiscal_quarter":1,"revenue":4239600000.0,"gross_profit":null,"operating_income":813500000.0,"net_income":540700000.0,"eps_diluted":0.71},{"period_end":"2014-03-30","period_type":"A","fiscal_year":2015,"fiscal_quarter":null,"revenue":3873800000.0,"gross_profit":null,"operating_income":644100000.0,"net_income":427000000.0,"eps_diluted":0.28},{"period_end":"2014-03-30","period_type":"Q","fiscal_year":2015,"fiscal_quarter":2,"revenue":8113400000.0,"gross_profit":null,"operating_income":1457700000.0,"net_income":967600000.0,"eps_diluted":0.63},{"period_end":"2014-06-29","period_type":"A","fiscal_year":2015,"fiscal_quarter":null,"revenue":4153700000.0,"gross_profit":null,"operating_income":768500000.0,"net_income":512600000.0,"eps_diluted":0.34},{"period_end":"2014-06-29","period_type":"Q","fiscal_year":2015,"fiscal_quarter":3,"revenue":12267100000.0,"gross_profit":null,"operating_income":2226300000.0,"net_income":1480300000.0,"eps_diluted":0.97},{"period_end":"2014-09-28","period_type":"A","fiscal_year":2016,"fiscal_quarter":null,"revenue":16447800000.0,"gross_profit":null,"operating_income":3081100000.0,"net_income":2068100000.0,"eps_diluted":1.35},{"period_end":"2014-12-28","period_type":"A","fiscal_year":2016,"fiscal_quarter":null,"revenue":4803200000.0,"gross_profit":null,"operating_income":915500000.0,"net_income":983100000.0,"eps_diluted":0.65},{"period_end":"2014-12-28","period_type":"Q","fiscal_year":2016,"fiscal_quarter":1,"revenue":4803200000.0,"gross_profit":null,"operating_income":915500000.0,"net_income":983100000.0,"eps_diluted":0.65},{"period_end":"2015-03-29","period_type":"A","fiscal_year":2016,"fiscal_quarter":null,"revenue":4563500000.0,"gross_profit":null,"operating_income":777500000.0,"net_income":494900000.0,"eps_diluted":0.33},{"period_end":"2015-03-29","period_type":"Q","fiscal_year":2016,"fiscal_quarter":2,"revenue":9366800000.0,"gross_profit":null,"operating_income":1693100000.0,"net_income":1478300000.0,"eps_diluted":0.97},{"period_end":"2015-06-28","period_type":"A","fiscal_year":2016,"fiscal_quarter":null,"revenue":4881200000.0,"gross_profit":null,"operating_income":938600000.0,"net_income":626700000.0,"eps_diluted":0.41},{"period_end":"2015-06-28","period_type":"Q","fiscal_year":2016,"fiscal_quarter":3,"revenue":14247900000.0,"gross_profit":null,"operating_income":2631600000.0,"net_income":2104900000.0,"eps_diluted":1.39},{"period_end":"2015-09-27","period_type":"A","fiscal_year":2017,"fiscal_quarter":null,"revenue":19162700000.0,"gross_profit":null,"operating_income":3601000000.0,"net_income":2757400000.0,"eps_diluted":1.82},{"period_end":"2015-12-27","period_type":"A","fiscal_year":2017,"fiscal_quarter":null,"revenue":5373500000.0,"gross_profit":null,"operating_income":1058000000.0,"net_income":687600000.0,"eps_diluted":0.46},{"period_end":"2015-12-27","period_type":"Q","fiscal_year":2017,"fiscal_quarter":1,"revenue":5373500000.0,"gross_profit":null,"operating_income":1058000000.0,"net_income":687600000.0,"eps_diluted":0.46},{"period_end":"2016-03-27","period_type":"A","fiscal_year":2017,"fiscal_quarter":null,"revenue":4993200000.0,"gross_profit":null,"operating_income":864200000.0,"net_income":575100000.0,"eps_diluted":0.39},{"period_end":"2016-03-27","period_type":"Q","fiscal_year":2017,"fiscal_quarter":2,"revenue":10366800000.0,"gross_profit":null,"operating_income":1922300000.0,"net_income":1262600000.0,"eps_diluted":0.84},{"period_end":"2016-06-26","period_type":"A","fiscal_year":2017,"fiscal_quarter":null,"revenue":5238000000.0,"gross_profit":null,"operating_income":1022300000.0,"net_income":754100000.0,"eps_diluted":0.51},{"period_end":"2016-06-26","period_type":"Q","fiscal_year":2017,"fiscal_quarter":3,"revenue":15604700000.0,"gross_profit":null,"operating_income":2944500000.0,"net_income":2016800000.0,"eps_diluted":1.35},{"period_end":"2016-10-02","period_type":"A","fiscal_year":2018,"fiscal_quarter":null,"revenue":21315900000.0,"gross_profit":null,"operating_income":4171900000.0,"net_income":2817700000.0,"eps_diluted":1.9},{"period_end":"2017-01-01","period_type":"A","fiscal_year":2018,"fiscal_quarter":null,"revenue":5732900000.0,"gross_profit":null,"operating_income":1132600000.0,"net_income":751800000.0,"eps_diluted":0.51},{"period_end":"2017-01-01","period_type":"Q","fiscal_year":2018,"fiscal_quarter":1,"revenue":5732900000.0,"gross_profit":null,"operating_income":1132600000.0,"net_income":751800000.0,"eps_diluted":0.51},{"period_end":"2017-04-02","period_type":"A","fiscal_year":2018,"fiscal_quarter":null,"revenue":5294000000.0,"gross_profit":null,"operating_income":935400000.0,"net_income":652800000.0,"eps_diluted":0.45},{"period_end":"2017-04-02","period_type":"Q","fiscal_year":2018,"fiscal_quarter":2,"revenue":11027000000.0,"gross_profit":null,"operating_income":2068300000.0,"net_income":1404900000.0,"eps_diluted":0.96},{"period_end":"2017-07-02","period_type":"A","fiscal_year":2018,"fiscal_quarter":null,"revenue":5661500000.0,"gross_profit":null,"operating_income":1044200000.0,"net_income":691600000.0,"eps_diluted":0.47},{"period_end":"2017-07-02","period_type":"Q","fiscal_year":2018,"fiscal_quarter":3,"revenue":16688500000.0,"gross_profit":null,"operating_income":3112100000.0,"net_income":2096100000.0,"eps_diluted":1.43},{"period_end":"2017-10-01","period_type":"A","fiscal_year":2019,"fiscal_quarter":null,"revenue":22386800000.0,"gross_profit":null,"operating_income":4134700000.0,"net_income":2884700000.0,"eps_diluted":1.97},{"period_end":"2017-12-31","period_type":"A","fiscal_year":2019,"fiscal_quarter":null,"revenue":6073700000.0,"gross_profit":null,"operating_income":1116100000.0,"net_income":2250200000.0,"eps_diluted":1.57},{"period_end":"2017-12-31","period_type":"Q","fiscal_year":2019,"fiscal_quarter":1,"revenue":6073700000.0,"gross_profit":null,"operating_income":1116100000.0,"net_income":2250200000.0,"eps_diluted":1.57},{"period_end":"2018-04-01","period_type":"A","fiscal_year":2019,"fiscal_quarter":null,"revenue":6031800000.0,"gross_profit":null,"operating_income":772500000.0,"net_income":660100000.0,"eps_diluted":0.47},{"period_end":"2018-04-01","period_type":"Q","fiscal_year":2019,"fiscal_quarter":2,"revenue":12105500000.0,"gross_profit":null,"operating_income":1888600000.0,"net_income":2910300000.0,"eps_diluted":2.05},{"period_end":"2018-07-01","period_type":"A","fiscal_year":2019,"fiscal_quarter":null,"revenue":6310300000.0,"gross_profit":null,"operating_income":1038200000.0,"net_income":852500000.0,"eps_diluted":0.61},{"period_end":"2018-07-01","period_type":"Q","fiscal_year":2019,"fiscal_quarter":3,"revenue":18415900000.0,"gross_profit":null,"operating_income":2926900000.0,"net_income":3762800000.0,"eps_diluted":2.67},{"period_end":"2018-09-30","period_type":"A","fiscal_year":2020,"fiscal_quarter":null,"revenue":24719500000.0,"gross_profit":null,"operating_income":3883300000.0,"net_income":4518300000.0,"eps_diluted":3.24},{"period_end":"2018-12-30","period_type":"A","fiscal_year":2020,"fiscal_quarter":null,"revenue":6632700000.0,"gross_profit":null,"operating_income":1015700000.0,"net_income":760600000.0,"eps_diluted":0.61},{"period_end":"2018-12-30","period_type":"Q","fiscal_year":2020,"fiscal_quarter":1,"revenue":6632700000.0,"gross_profit":null,"operating_income":1015700000.0,"net_income":760600000.0,"eps_diluted":0.61},{"period_end":"2019-03-31","period_type":"A","fiscal_year":2020,"fiscal_quarter":null,"revenue":6305900000.0,"gross_profit":null,"operating_income":857700000.0,"net_income":663200000.0,"eps_diluted":0.53},{"period_end":"2019-03-31","period_type":"Q","fiscal_year":2020,"fiscal_quarter":2,"revenue":12938700000.0,"gross_profit":null,"operating_income":1873400000.0,"net_income":1423600000.0,"eps_diluted":1.14},{"period_end":"2019-06-30","period_type":"A","fiscal_year":2020,"fiscal_quarter":null,"revenue":6823000000.0,"gross_profit":null,"operating_income":1121300000.0,"net_income":1372800000.0,"eps_diluted":1.12},{"period_end":"2019-06-30","period_type":"Q","fiscal_year":2020,"fiscal_quarter":3,"revenue":19761600000.0,"gross_profit":null,"operating_income":2994600000.0,"net_income":2796400000.0,"eps_diluted":2.25},{"period_end":"2019-09-29","period_type":"A","fiscal_year":2021,"fiscal_quarter":null,"revenue":26508600000.0,"gross_profit":null,"operating_income":4077900000.0,"net_income":3599200000.0,"eps_diluted":2.92},{"period_end":"2019-12-29","period_type":"A","fiscal_year":2020,"fiscal_quarter":null,"revenue":7097100000.0,"gross_profit":null,"operating_income":1219800000.0,"net_income":885700000.0,"eps_diluted":0.74},{"period_end":"2019-12-29","period_type":"Q","fiscal_year":2021,"fiscal_quarter":1,"revenue":7097100000.0,"gross_profit":null,"operating_income":1219800000.0,"net_income":885700000.0,"eps_diluted":0.74},{"period_end":"2020-03-29","period_type":"A","fiscal_year":2020,"fiscal_quarter":null,"revenue":5995700000.0,"gross_profit":null,"operating_income":487400000.0,"net_income":328400000.0,"eps_diluted":0.28},{"period_end":"2020-03-29","period_type":"Q","fiscal_year":2021,"fiscal_quarter":2,"revenue":13092800000.0,"gross_profit":null,"operating_income":1707200000.0,"net_income":1214100000.0,"eps_diluted":1.02},{"period_end":"2020-06-28","period_type":"A","fiscal_year":2020,"fiscal_quarter":null,"revenue":4222100000.0,"gross_profit":null,"operating_income":-703900000.0,"net_income":-678400000.0,"eps_diluted":-0.58},{"period_end":"2020-06-28","period_type":"Q","fiscal_year":2021,"fiscal_quarter":3,"revenue":17314900000.0,"gross_profit":null,"operating_income":1003400000.0,"net_income":535700000.0,"eps_diluted":0.45},{"period_end":"2020-09-27","period_type":"A","fiscal_year":2022,"fiscal_quarter":null,"revenue":23518000000.0,"gross_profit":null,"operating_income":1561700000.0,"net_income":928300000.0,"eps_diluted":0.79},{"period_end":"2020-12-27","period_type":"Q","fiscal_year":2022,"fiscal_quarter":1,"revenue":6749400000.0,"gross_profit":null,"operating_income":913500000.0,"net_income":622200000.0,"eps_diluted":0.53},{"period_end":"2021-03-28","period_type":"Q","fiscal_year":2022,"fiscal_quarter":2,"revenue":13417500000.0,"gross_profit":null,"operating_income":1901200000.0,"net_income":1281600000.0,"eps_diluted":1.08},{"period_end":"2021-06-27","period_type":"Q","fiscal_year":2022,"fiscal_quarter":3,"revenue":20913900000.0,"gross_profit":null,"operating_income":3389900000.0,"net_income":2434900000.0,"eps_diluted":2.06},{"period_end":"2021-10-03","period_type":"A","fiscal_year":2023,"fiscal_quarter":null,"revenue":29060600000.0,"gross_profit":null,"operating_income":4872100000.0,"net_income":4199300000.0,"eps_diluted":3.54},{"period_end":"2022-01-02","period_type":"Q","fiscal_year":2023,"fiscal_quarter":1,"revenue":8050400000.0,"gross_profit":null,"operating_income":1177800000.0,"net_income":815900000.0,"eps_diluted":0.69},{"period_end":"2022-04-03","period_type":"Q","fiscal_year":2023,"fiscal_quarter":2,"revenue":15686000000.0,"gross_profit":null,"operating_income":2126700000.0,"net_income":1490400000.0,"eps_diluted":1.28},{"period_end":"2022-07-03","period_type":"Q","fiscal_year":2023,"fiscal_quarter":3,"revenue":23836100000.0,"gross_profit":null,"operating_income":3422300000.0,"net_income":2403300000.0,"eps_diluted":2.07},{"period_end":"2022-10-02","period_type":"A","fiscal_year":2024,"fiscal_quarter":null,"revenue":32250300000.0,"gross_profit":null,"operating_income":4617800000.0,"net_income":3281600000.0,"eps_diluted":2.83},{"period_end":"2023-01-01","period_type":"Q","fiscal_year":2024,"fiscal_quarter":1,"revenue":8713900000.0,"gross_profit":null,"operating_income":1253100000.0,"net_income":855200000.0,"eps_diluted":0.74},{"period_end":"2023-04-02","period_type":"Q","fiscal_year":2024,"fiscal_quarter":2,"revenue":17433800000.0,"gross_profit":null,"operating_income":2580700000.0,"net_income":1763600000.0,"eps_diluted":1.53},{"period_end":"2023-07-02","period_type":"Q","fiscal_year":2024,"fiscal_quarter":3,"revenue":26602000000.0,"gross_profit":null,"operating_income":4164600000.0,"net_income":2905200000.0,"eps_diluted":2.52},{"period_end":"2023-10-01","period_type":"A","fiscal_year":2025,"fiscal_quarter":null,"revenue":35975600000.0,"gross_profit":null,"operating_income":5870800000.0,"net_income":4124500000.0,"eps_diluted":3.58},{"period_end":"2023-12-31","period_type":"Q","fiscal_year":2025,"fiscal_quarter":1,"revenue":9425300000.0,"gross_profit":null,"operating_income":1485400000.0,"net_income":1024400000.0,"eps_diluted":0.9},{"period_end":"2024-03-31","period_type":"Q","fiscal_year":2025,"fiscal_quarter":2,"revenue":17988300000.0,"gross_profit":null,"operating_income":2584300000.0,"net_income":1796800000.0,"eps_diluted":1.58},{"period_end":"2024-06-30","period_type":"Q","fiscal_year":2025,"fiscal_quarter":3,"revenue":27102300000.0,"gross_profit":null,"operating_income":4101900000.0,"net_income":2851700000.0,"eps_diluted":2.51},{"period_end":"2024-09-29","period_type":"A","fiscal_year":2025,"fiscal_quarter":null,"revenue":36176200000.0,"gross_profit":null,"operating_income":5408800000.0,"net_income":3760900000.0,"eps_diluted":3.31},{"period_end":"2024-12-29","period_type":"Q","fiscal_year":2026,"fiscal_quarter":1,"revenue":9397800000.0,"gross_profit":null,"operating_income":1121700000.0,"net_income":780800000.0,"eps_diluted":0.69},{"period_end":"2025-03-30","period_type":"Q","fiscal_year":2025,"fiscal_quarter":2,"revenue":18159400000.0,"gross_profit":null,"operating_income":1722800000.0,"net_income":1165000000.0,"eps_diluted":1.02},{"period_end":"2025-06-29","period_type":"Q","fiscal_year":2025,"fiscal_quarter":3,"revenue":27615400000.0,"gross_profit":null,"operating_income":2658400000.0,"net_income":1723200000.0,"eps_diluted":1.51},{"period_end":"2025-09-28","period_type":"A","fiscal_year":2025,"fiscal_quarter":null,"revenue":37184400000.0,"gross_profit":null,"operating_income":2936600000.0,"net_income":1856400000.0,"eps_diluted":1.63},{"period_end":"2025-12-28","period_type":"Q","fiscal_year":2026,"fiscal_quarter":1,"revenue":9915100000.0,"gross_profit":null,"operating_income":890800000.0,"net_income":293300000.0,"eps_diluted":0.26}],"balance_sheets":[{"period_end":"2006-10-01","period_type":"A","cash":312600000.0,"total_assets":null,"long_term_debt":null,"total_liabilities":null,"stockholders_equity":2228500000.0},{"period_end":"2007-09-30","period_type":"A","cash":281300000.0,"total_assets":null,"long_term_debt":null,"total_liabilities":null,"stockholders_equity":2301400000.0},{"period_end":"2007-09-30","period_type":"Q","cash":281300000.0,"total_assets":null,"long_term_debt":null,"total_liabilities":null,"stockholders_equity":null},{"period_end":"2008-06-29","period_type":"Q","cash":297000000.0,"total_assets":null,"long_term_debt":null,"total_liabilities":null,"stockholders_equity":null},{"period_end":"2008-09-28","period_type":"A","cash":269800000.0,"total_assets":5672600000.0,"long_term_debt":549600000.0,"total_liabilities":3181700000.0,"stockholders_equity":2509200000.0},{"period_end":"2008-09-28","period_type":"Q","cash":269800000.0,"total_assets":5672600000.0,"long_term_debt":549600000.0,"total_liabilities":3181700000.0,"stockholders_equity":2509200000.0},{"period_end":"2008-12-28","period_type":"Q","cash":356800000.0,"total_assets":null,"long_term_debt":null,"total_liabilities":null,"stockholders_equity":null},{"period_end":"2009-03-29","period_type":"Q","cash":253200000.0,"total_assets":null,"long_term_debt":null,"total_liabilities":null,"stockholders_equity":null},{"period_end":"2009-06-28","period_type":"Q","cash":292000000.0,"total_assets":5333100000.0,"long_term_debt":549400000.0,"total_liabilities":2515100000.0,"stockholders_equity":2833500000.0},{"period_end":"2009-09-27","period_type":"A","cash":599800000.0,"total_assets":5576800000.0,"long_term_debt":549500000.0,"total_liabilities":2519900000.0,"stockholders_equity":3056900000.0},{"period_end":"2009-09-27","period_type":"Q","cash":599800000.0,"total_assets":5576800000.0,"long_term_debt":549500000.0,"total_liabilities":2519900000.0,"stockholders_equity":3056900000.0},{"period_end":"2009-12-27","period_type":"Q","cash":1306300000.0,"total_assets":6101600000.0,"long_term_debt":549300000.0,"total_liabilities":2737500000.0,"stockholders_equity":3364100000.0},{"period_end":"2010-03-28","period_type":"Q","cash":1086000000.0,"total_assets":6144700000.0,"long_term_debt":549300000.0,"total_liabilities":2590000000.0,"stockholders_equity":3554700000.0},{"period_end":"2010-06-27","period_type":"Q","cash":1125200000.0,"total_assets":6206900000.0,"long_term_debt":549400000.0,"total_liabilities":2672300000.0,"stockholders_equity":3534600000.0},{"period_end":"2010-10-03","period_type":"A","cash":1164000000.0,"total_assets":6385900000.0,"long_term_debt":549400000.0,"total_liabilities":2703600000.0,"stockholders_equity":3682300000.0},{"period_end":"2010-10-03","period_type":"Q","cash":1164000000.0,"total_assets":6385900000.0,"long_term_debt":549400000.0,"total_liabilities":2703600000.0,"stockholders_equity":3682300000.0},{"period_end":"2011-01-02","period_type":"Q","cash":1792000000.0,"total_assets":6931100000.0,"long_term_debt":549400000.0,"total_liabilities":2870800000.0,"stockholders_equity":4060300000.0},{"period_end":"2011-04-03","period_type":"Q","cash":1645200000.0,"total_assets":7027600000.0,"long_term_debt":549400000.0,"total_liabilities":2700400000.0,"stockholders_equity":4327200000.0},{"period_end":"2011-07-03","period_type":"Q","cash":1720800000.0,"total_assets":7097800000.0,"long_term_debt":549400000.0,"total_liabilities":2756300000.0,"stockholders_equity":4341500000.0},{"period_end":"2011-10-02","period_type":"A","cash":1148100000.0,"total_assets":7360400000.0,"long_term_debt":549500000.0,"total_liabilities":2973100000.0,"stockholders_equity":4387300000.0},{"period_end":"2011-10-02","period_type":"Q","cash":1148100000.0,"total_assets":7360400000.0,"long_term_debt":549500000.0,"total_liabilities":2973100000.0,"stockholders_equity":4387300000.0},{"period_end":"2012-01-01","period_type":"Q","cash":1569600000.0,"total_assets":7835600000.0,"long_term_debt":549500000.0,"total_liabilities":3060300000.0,"stockholders_equity":4775300000.0},{"period_end":"2012-04-01","period_type":"Q","cash":1432200000.0,"total_assets":8006500000.0,"long_term_debt":549600000.0,"total_liabilities":2869800000.0,"stockholders_equity":5136700000.0},{"period_end":"2012-07-01","period_type":"Q","cash":1501300000.0,"total_assets":8308900000.0,"long_term_debt":549600000.0,"total_liabilities":2920900000.0,"stockholders_equity":5388000000.0},{"period_end":"2012-09-30","period_type":"A","cash":1188600000.0,"total_assets":8219200000.0,"long_term_debt":549600000.0,"total_liabilities":3104700000.0,"stockholders_equity":5114500000.0},{"period_end":"2012-09-30","period_type":"Q","cash":1188600000.0,"total_assets":8219200000.0,"long_term_debt":549600000.0,"total_liabilities":3104700000.0,"stockholders_equity":5114500000.0},{"period_end":"2012-12-30","period_type":"Q","cash":1852100000.0,"total_assets":8490100000.0,"long_term_debt":549600000.0,"total_liabilities":3315100000.0,"stockholders_equity":5175000000.0},{"period_end":"2013-03-31","period_type":"Q","cash":1223200000.0,"total_assets":8502800000.0,"long_term_debt":549600000.0,"total_liabilities":3175300000.0,"stockholders_equity":5327500000.0},{"period_end":"2013-06-30","period_type":"Q","cash":1430800000.0,"total_assets":9062400000.0,"long_term_debt":549700000.0,"total_liabilities":3314800000.0,"stockholders_equity":5747600000.0},{"period_end":"2013-09-29","period_type":"A","cash":2575700000.0,"total_assets":11516700000.0,"long_term_debt":1299400000.0,"total_liabilities":7034400000.0,"stockholders_equity":4482300000.0},{"period_end":"2013-09-29","period_type":"Q","cash":2575700000.0,"total_assets":11516700000.0,"long_term_debt":1299400000.0,"total_liabilities":7034400000.0,"stockholders_equity":4482300000.0},{"period_end":"2013-12-29","period_type":"Q","cash":1545800000.0,"total_assets":10255200000.0,"long_term_debt":2047900000.0,"total_liabilities":5365700000.0,"stockholders_equity":4889500000.0},{"period_end":"2014-03-30","period_type":"Q","cash":1190300000.0,"total_assets":10097000000.0,"long_term_debt":2048000000.0,"total_liabilities":5149900000.0,"stockholders_equity":4947100000.0},{"period_end":"2014-06-29","period_type":"Q","cash":1019400000.0,"total_assets":10385300000.0,"long_term_debt":2048100000.0,"total_liabilities":5314500000.0,"stockholders_equity":5070800000.0},{"period_end":"2014-09-28","period_type":"A","cash":1708400000.0,"total_assets":10752900000.0,"long_term_debt":2048300000.0,"total_liabilities":5479200000.0,"stockholders_equity":5273700000.0},{"period_end":"2014-09-28","period_type":"Q","cash":1708400000.0,"total_assets":10752900000.0,"long_term_debt":2048300000.0,"total_liabilities":5479200000.0,"stockholders_equity":5273700000.0},{"period_end":"2014-12-28","period_type":"Q","cash":1857000000.0,"total_assets":12351100000.0,"long_term_debt":2048400000.0,"total_liabilities":6193300000.0,"stockholders_equity":6157800000.0},{"period_end":"2015-03-29","period_type":"Q","cash":1750400000.0,"total_assets":12190700000.0,"long_term_debt":2048500000.0,"total_liabilities":6180000000.0,"stockholders_equity":6010700000.0},{"period_end":"2015-06-28","period_type":"Q","cash":2080500000.0,"total_assets":12868800000.0,"long_term_debt":2897200000.0,"total_liabilities":7010500000.0,"stockholders_equity":5858300000.0},{"period_end":"2015-09-27","period_type":"A","cash":1530100000.0,"total_assets":12416300000.0,"long_term_debt":2347500000.0,"total_liabilities":6596500000.0,"stockholders_equity":5819800000.0},{"period_end":"2015-09-27","period_type":"Q","cash":1530100000.0,"total_assets":12416300000.0,"long_term_debt":2347500000.0,"total_liabilities":6596500000.0,"stockholders_equity":5819800000.0},{"period_end":"2015-12-27","period_type":"Q","cash":2263500000.0,"total_assets":12943500000.0,"long_term_debt":2347700000.0,"total_liabilities":6960100000.0,"stockholders_equity":5983400000.0},{"period_end":"2016-03-27","period_type":"Q","cash":1294400000.0,"total_assets":12519400000.0,"long_term_debt":2847400000.0,"total_liabilities":7423000000.0,"stockholders_equity":5096400000.0},{"period_end":"2016-06-26","period_type":"Q","cash":2141800000.0,"total_assets":13833200000.0,"long_term_debt":3602200000.0,"total_liabilities":8109200000.0,"stockholders_equity":5724000000.0},{"period_end":"2016-10-02","period_type":"A","cash":2128800000.0,"total_assets":14312500000.0,"long_term_debt":3585200000.0,"total_liabilities":8421800000.0,"stockholders_equity":5890700000.0},{"period_end":"2016-10-02","period_type":"Q","cash":2128800000.0,"total_assets":14312500000.0,"long_term_debt":3585200000.0,"total_liabilities":8421800000.0,"stockholders_equity":5890700000.0},{"period_end":"2017-01-01","period_type":"Q","cash":2034600000.0,"total_assets":14017300000.0,"long_term_debt":3185700000.0,"total_liabilities":8214200000.0,"stockholders_equity":5803100000.0},{"period_end":"2017-04-02","period_type":"Q","cash":2163900000.0,"total_assets":14227900000.0,"long_term_debt":3942500000.0,"total_liabilities":8616500000.0,"stockholders_equity":5611400000.0},{"period_end":"2017-07-02","period_type":"Q","cash":2716200000.0,"total_assets":14522700000.0,"long_term_debt":3935500000.0,"total_liabilities":8673200000.0,"stockholders_equity":5849500000.0},{"period_end":"2017-10-01","period_type":"A","cash":2462300000.0,"total_assets":14365600000.0,"long_term_debt":3932600000.0,"total_liabilities":8908600000.0,"stockholders_equity":5457000000.0},{"period_end":"2017-10-01","period_type":"Q","cash":2462300000.0,"total_assets":14365600000.0,"long_term_debt":3932600000.0,"total_liabilities":8908600000.0,"stockholders_equity":5457000000.0},{"period_end":"2017-12-31","period_type":"Q","cash":3661400000.0,"total_assets":18518500000.0,"long_term_debt":4916400000.0,"total_liabilities":12759600000.0,"stockholders_equity":5758900000.0},{"period_end":"2018-04-01","period_type":"Q","cash":2142000000.0,"total_assets":17553500000.0,"long_term_debt":6534800000.0,"total_liabilities":12835800000.0,"stockholders_equity":4717700000.0},{"period_end":"2018-07-01","period_type":"Q","cash":1892100000.0,"total_assets":17182100000.0,"long_term_debt":6498900000.0,"total_liabilities":13185400000.0,"stockholders_equity":3996700000.0},{"period_end":"2018-09-30","period_type":"A","cash":8756300000.0,"total_assets":24156400000.0,"long_term_debt":9440100000.0,"total_liabilities":22980600000.0,"stockholders_equity":1175800000.0},{"period_end":"2018-09-30","period_type":"Q","cash":8756300000.0,"total_assets":24156400000.0,"long_term_debt":9440100000.0,"total_liabilities":22980600000.0,"stockholders_equity":1175800000.0},{"period_end":"2018-10-01","period_type":"A","cash":null,"total_assets":null,"long_term_debt":null,"total_liabilities":null,"stockholders_equity":null},{"period_end":"2018-10-01","period_type":"Q","cash":null,"total_assets":null,"long_term_debt":null,"total_liabilities":null,"stockholders_equity":null},{"period_end":"2018-12-30","period_type":"Q","cash":4761600000.0,"total_assets":19981300000.0,"long_term_debt":9130700000.0,"total_liabilities":22860100000.0,"stockholders_equity":-2878800000.0},{"period_end":"2019-03-31","period_type":"Q","cash":2055100000.0,"total_assets":17641900000.0,"long_term_debt":9141500000.0,"total_liabilities":22677100000.0,"stockholders_equity":-5035200000.0},{"period_end":"2019-06-30","period_type":"Q","cash":4763300000.0,"total_assets":20894400000.0,"long_term_debt":11159100000.0,"total_liabilities":25213400000.0,"stockholders_equity":-4319000000.0},{"period_end":"2019-09-29","period_type":"A","cash":2686600000.0,"total_assets":19219600000.0,"long_term_debt":11167000000.0,"total_liabilities":25450600000.0,"stockholders_equity":-6231000000.0},{"period_end":"2019-09-29","period_type":"Q","cash":2686600000.0,"total_assets":19219600000.0,"long_term_debt":11167000000.0,"total_liabilities":25450600000.0,"stockholders_equity":-6231000000.0},{"period_end":"2019-12-29","period_type":"Q","cash":3040500000.0,"total_assets":27731300000.0,"long_term_debt":11151900000.0,"total_liabilities":34490400000.0,"stockholders_equity":-6759100000.0},{"period_end":"2020-03-29","period_type":"Q","cash":2572300000.0,"total_assets":27478900000.0,"long_term_debt":12908100000.0,"total_liabilities":35011800000.0,"stockholders_equity":-7532900000.0},{"period_end":"2020-06-28","period_type":"Q","cash":3965900000.0,"total_assets":29140600000.0,"long_term_debt":15895200000.0,"total_liabilities":37764900000.0,"stockholders_equity":-8624300000.0},{"period_end":"2020-09-27","period_type":"A","cash":4350900000.0,"total_assets":29374500000.0,"long_term_debt":15909500000.0,"total_liabilities":37173900000.0,"stockholders_equity":-7799400000.0},{"period_end":"2020-09-27","period_type":"Q","cash":4350900000.0,"total_assets":29374500000.0,"long_term_debt":15909500000.0,"total_liabilities":37173900000.0,"stockholders_equity":-7799400000.0},{"period_end":"2020-12-27","period_type":"Q","cash":5028100000.0,"total_assets":29968400000.0,"long_term_debt":15423500000.0,"total_liabilities":37872400000.0,"stockholders_equity":-7904000000.0},{"period_end":"2021-03-28","period_type":"Q","cash":3880700000.0,"total_assets":28371700000.0,"long_term_debt":14630300000.0,"total_liabilities":36020000000.0,"stockholders_equity":-7648300000.0},{"period_end":"2021-06-27","period_type":"Q","cash":4753100000.0,"total_assets":29476800000.0,"long_term_debt":14618100000.0,"total_liabilities":36271100000.0,"stockholders_equity":-6794300000.0},{"period_end":"2021-10-03","period_type":"A","cash":6455700000.0,"total_assets":31392600000.0,"long_term_debt":14615800000.0,"total_liabilities":36707100000.0,"stockholders_equity":-5314500000.0},{"period_end":"2021-10-03","period_type":"Q","cash":6455700000.0,"total_assets":31392600000.0,"long_term_debt":14615800000.0,"total_liabilities":36707100000.0,"stockholders_equity":-5314500000.0},{"period_end":"2022-01-02","period_type":"Q","cash":3969400000.0,"total_assets":28833900000.0,"long_term_debt":14585600000.0,"total_liabilities":37284200000.0,"stockholders_equity":-8450300000.0},{"period_end":"2022-04-03","period_type":"Q","cash":3913400000.0,"total_assets":29021500000.0,"long_term_debt":16013000000.0,"total_liabilities":37782700000.0,"stockholders_equity":-8761200000.0},{"period_end":"2022-07-03","period_type":"Q","cash":3177500000.0,"total_assets":28156200000.0,"long_term_debt":14929900000.0,"total_liabilities":36815100000.0,"stockholders_equity":-8658900000.0},{"period_end":"2022-10-02","period_type":"A","cash":null,"total_assets":27978400000.0,"long_term_debt":14868900000.0,"total_liabilities":36677100000.0,"stockholders_equity":-8698700000.0},{"period_end":"2022-10-02","period_type":"Q","cash":null,"total_assets":27978400000.0,"long_term_debt":14868900000.0,"total_liabilities":36677100000.0,"stockholders_equity":-8698700000.0},{"period_end":"2023-01-01","period_type":"Q","cash":null,"total_assets":28256100000.0,"long_term_debt":14926000000.0,"total_liabilities":36922000000.0,"stockholders_equity":-8665900000.0},{"period_end":"2023-04-02","period_type":"Q","cash":null,"total_assets":28609000000.0,"long_term_debt":15433500000.0,"total_liabilities":37108400000.0,"stockholders_equity":-8499400000.0},{"period_end":"2023-07-02","period_type":"Q","cash":null,"total_assets":28733000000.0,"long_term_debt":15380300000.0,"total_liabilities":37074600000.0,"stockholders_equity":-8341600000.0},{"period_end":"2023-10-01","period_type":"A","cash":null,"total_assets":29445500000.0,"long_term_debt":15366200000.0,"total_liabilities":37433300000.0,"stockholders_equity":-7987800000.0},{"period_end":"2023-10-01","period_type":"Q","cash":null,"total_assets":29445500000.0,"long_term_debt":15366200000.0,"total_liabilities":37433300000.0,"stockholders_equity":-7987800000.0},{"period_end":"2023-12-31","period_type":"Q","cash":null,"total_assets":29179700000.0,"long_term_debt":14665600000.0,"total_liabilities":37788600000.0,"stockholders_equity":-8608900000.0},{"period_end":"2024-03-31","period_type":"Q","cash":null,"total_assets":29363200000.0,"long_term_debt":15547500000.0,"total_liabilities":37805400000.0,"stockholders_equity":-8442200000.0},{"period_end":"2024-06-30","period_type":"Q","cash":null,"total_assets":30111800000.0,"long_term_debt":15551400000.0,"total_liabilities":38049200000.0,"stockholders_equity":-7937400000.0},{"period_end":"2024-09-29","period_type":"A","cash":null,"total_assets":31339300000.0,"long_term_debt":15568400000.0,"total_liabilities":38780900000.0,"stockholders_equity":-7448900000.0},{"period_end":"2024-09-29","period_type":"Q","cash":null,"total_assets":31339300000.0,"long_term_debt":15568400000.0,"total_liabilities":38780900000.0,"stockholders_equity":-7441600000.0},{"period_end":"2024-12-29","period_type":"Q","cash":null,"total_assets":31893100000.0,"long_term_debt":15561400000.0,"total_liabilities":39357700000.0,"stockholders_equity":-7464600000.0},{"period_end":"2025-03-30","period_type":"Q","cash":null,"total_assets":31633100000.0,"long_term_debt":15571800000.0,"total_liabilities":39248500000.0,"stockholders_equity":-7615400000.0},{"period_end":"2025-06-29","period_type":"Q","cash":null,"total_assets":33649200000.0,"long_term_debt":17319100000.0,"total_liabilities":41327800000.0,"stockholders_equity":-7686000000.0},{"period_end":"2025-09-28","period_type":"A","cash":null,"total_assets":32019700000.0,"long_term_debt":16074800000.0,"total_liabilities":40108900000.0,"stockholders_equity":-8096600000.0},{"period_end":"2025-09-28","period_type":"Q","cash":null,"total_assets":32019700000.0,"long_term_debt":16074800000.0,"total_liabilities":40108900000.0,"stockholders_equity":-8096600000.0},{"period_end":"2025-12-28","period_type":"Q","cash":null,"total_assets":32228300000.0,"long_term_debt":16080400000.0,"total_liabilities":40609600000.0,"stockholders_equity":-8388700000.0}],"cash_flows":[{"period_end":"2007-09-30","period_type":"A","operating_cf":1331200000.0,"capex":1080300000.0,"dividends_paid":null,"free_cash_flow":250900000.0},{"period_end":"2008-06-29","period_type":"Q","operating_cf":1078700000.0,"capex":733900000.0,"dividends_paid":null,"free_cash_flow":344800000.0},{"period_end":"2008-09-28","period_type":"A","operating_cf":1258700000.0,"capex":984500000.0,"dividends_paid":0.0,"free_cash_flow":274200000.0},{"period_end":"2008-12-28","period_type":"Q","operating_cf":693500000.0,"capex":172600000.0,"dividends_paid":null,"free_cash_flow":520900000.0},{"period_end":"2009-03-29","period_type":"Q","operating_cf":715400000.0,"capex":236900000.0,"dividends_paid":null,"free_cash_flow":478500000.0},{"period_end":"2009-06-28","period_type":"Q","operating_cf":1016700000.0,"capex":344200000.0,"dividends_paid":0.0,"free_cash_flow":672500000.0},{"period_end":"2009-09-27","period_type":"A","operating_cf":1389000000.0,"capex":445600000.0,"dividends_paid":0.0,"free_cash_flow":943400000.0},{"period_end":"2009-12-27","period_type":"Q","operating_cf":768700000.0,"capex":99700000.0,"dividends_paid":0.0,"free_cash_flow":669000000.0},{"period_end":"2010-03-28","period_type":"Q","operating_cf":957800000.0,"capex":184500000.0,"dividends_paid":0.0,"free_cash_flow":773300000.0},{"period_end":"2010-06-27","period_type":"Q","operating_cf":1375400000.0,"capex":281100000.0,"dividends_paid":74800000.0,"free_cash_flow":1094300000.0},{"period_end":"2010-10-03","period_type":"A","operating_cf":1704900000.0,"capex":445800000.0,"dividends_paid":171000000.0,"free_cash_flow":1259100000.0},{"period_end":"2011-01-02","period_type":"Q","operating_cf":673600000.0,"capex":128900000.0,"dividends_paid":96900000.0,"free_cash_flow":544700000.0},{"period_end":"2011-04-03","period_type":"Q","operating_cf":669500000.0,"capex":239100000.0,"dividends_paid":194300000.0,"free_cash_flow":430400000.0},{"period_end":"2011-07-03","period_type":"Q","operating_cf":1126700000.0,"capex":372400000.0,"dividends_paid":292100000.0,"free_cash_flow":754300000.0},{"period_end":"2011-10-02","period_type":"A","operating_cf":1612400000.0,"capex":531900000.0,"dividends_paid":389500000.0,"free_cash_flow":1080500000.0},{"period_end":"2012-01-01","period_type":"Q","operating_cf":466300000.0,"capex":153500000.0,"dividends_paid":126800000.0,"free_cash_flow":312800000.0},{"period_end":"2012-04-01","period_type":"Q","operating_cf":575600000.0,"capex":313800000.0,"dividends_paid":255000000.0,"free_cash_flow":261800000.0},{"period_end":"2012-07-01","period_type":"Q","operating_cf":1126900000.0,"capex":516500000.0,"dividends_paid":384000000.0,"free_cash_flow":610400000.0},{"period_end":"2012-09-30","period_type":"A","operating_cf":1750300000.0,"capex":856200000.0,"dividends_paid":513000000.0,"free_cash_flow":894100000.0},{"period_end":"2012-12-30","period_type":"Q","operating_cf":1067300000.0,"capex":244500000.0,"dividends_paid":156100000.0,"free_cash_flow":822800000.0},{"period_end":"2013-03-31","period_type":"Q","operating_cf":1372500000.0,"capex":484900000.0,"dividends_paid":313500000.0,"free_cash_flow":887600000.0},{"period_end":"2013-06-30","period_type":"Q","operating_cf":2037800000.0,"capex":782200000.0,"dividends_paid":470900000.0,"free_cash_flow":1255600000.0},{"period_end":"2013-09-29","period_type":"A","operating_cf":2908300000.0,"capex":1151200000.0,"dividends_paid":628900000.0,"free_cash_flow":1757100000.0},{"period_end":"2013-12-29","period_type":"Q","operating_cf":-1401900000.0,"capex":256100000.0,"dividends_paid":195900000.0,"free_cash_flow":-1658000000.0},{"period_end":"2014-03-30","period_type":"Q","operating_cf":-983500000.0,"capex":503600000.0,"dividends_paid":392300000.0,"free_cash_flow":-1487100000.0},{"period_end":"2014-06-29","period_type":"Q","operating_cf":-133400000.0,"capex":811200000.0,"dividends_paid":587800000.0,"free_cash_flow":-944600000.0},{"period_end":"2014-09-28","period_type":"A","operating_cf":607800000.0,"capex":1160900000.0,"dividends_paid":783100000.0,"free_cash_flow":-553100000.0},{"period_end":"2014-12-28","period_type":"Q","operating_cf":1425200000.0,"capex":291800000.0,"dividends_paid":239500000.0,"free_cash_flow":1133400000.0},{"period_end":"2015-03-29","period_type":"Q","operating_cf":2000900000.0,"capex":606600000.0,"dividends_paid":479600000.0,"free_cash_flow":1394300000.0},{"period_end":"2015-06-28","period_type":"Q","operating_cf":2779200000.0,"capex":943500000.0,"dividends_paid":719700000.0,"free_cash_flow":1835700000.0},{"period_end":"2015-09-27","period_type":"A","operating_cf":3749100000.0,"capex":1303700000.0,"dividends_paid":928600000.0,"free_cash_flow":2445400000.0},{"period_end":"2015-12-27","period_type":"Q","operating_cf":1636000000.0,"capex":331800000.0,"dividends_paid":297000000.0,"free_cash_flow":1304200000.0},{"period_end":"2016-03-27","period_type":"Q","operating_cf":2185500000.0,"capex":668200000.0,"dividends_paid":591800000.0,"free_cash_flow":1517300000.0},{"period_end":"2016-06-26","period_type":"Q","operating_cf":3266900000.0,"capex":1029700000.0,"dividends_paid":884800000.0,"free_cash_flow":2237200000.0},{"period_end":"2016-10-02","period_type":"A","operating_cf":4697900000.0,"capex":1440300000.0,"dividends_paid":1178000000.0,"free_cash_flow":3257600000.0},{"period_end":"2017-01-01","period_type":"Q","operating_cf":1529800000.0,"capex":307400000.0,"dividends_paid":364000000.0,"free_cash_flow":1222400000.0},{"period_end":"2017-04-02","period_type":"Q","operating_cf":1991700000.0,"capex":637900000.0,"dividends_paid":727800000.0,"free_cash_flow":1353800000.0},{"period_end":"2017-07-02","period_type":"Q","operating_cf":3159000000.0,"capex":1025300000.0,"dividends_paid":1089800000.0,"free_cash_flow":2133700000.0},{"period_end":"2017-10-01","period_type":"A","operating_cf":4251800000.0,"capex":1519400000.0,"dividends_paid":1450400000.0,"free_cash_flow":2732400000.0},{"period_end":"2017-12-31","period_type":"Q","operating_cf":1834000000.0,"capex":429300000.0,"dividends_paid":428100000.0,"free_cash_flow":1404700000.0},{"period_end":"2018-04-01","period_type":"Q","operating_cf":2288500000.0,"capex":896700000.0,"dividends_paid":847900000.0,"free_cash_flow":1391800000.0},{"period_end":"2018-07-01","period_type":"Q","operating_cf":3504400000.0,"capex":1407800000.0,"dividends_paid":1260200000.0,"free_cash_flow":2096600000.0},{"period_end":"2018-09-30","period_type":"A","operating_cf":11937800000.0,"capex":1976400000.0,"dividends_paid":1743400000.0,"free_cash_flow":9961400000.0},{"period_end":"2018-12-30","period_type":"Q","operating_cf":2379000000.0,"capex":431400000.0,"dividends_paid":446700000.0,"free_cash_flow":1947600000.0},{"period_end":"2019-03-31","period_type":"Q","operating_cf":2769400000.0,"capex":845600000.0,"dividends_paid":894500000.0,"free_cash_flow":1923800000.0},{"period_end":"2019-06-30","period_type":"Q","operating_cf":3938800000.0,"capex":1280700000.0,"dividends_paid":1330700000.0,"free_cash_flow":2658100000.0},{"period_end":"2019-09-29","period_type":"A","operating_cf":5047000000.0,"capex":1806600000.0,"dividends_paid":1761300000.0,"free_cash_flow":3240400000.0},{"period_end":"2019-12-29","period_type":"Q","operating_cf":1836100000.0,"capex":394300000.0,"dividends_paid":484200000.0,"free_cash_flow":1441800000.0},{"period_end":"2020-03-29","period_type":"Q","operating_cf":474800000.0,"capex":758300000.0,"dividends_paid":965200000.0,"free_cash_flow":-283500000.0},{"period_end":"2020-06-28","period_type":"Q","operating_cf":107100000.0,"capex":1138400000.0,"dividends_paid":1444200000.0,"free_cash_flow":-1031300000.0},{"period_end":"2020-09-27","period_type":"A","operating_cf":1597800000.0,"capex":1483600000.0,"dividends_paid":1923500000.0,"free_cash_flow":114200000.0},{"period_end":"2020-12-27","period_type":"Q","operating_cf":1835700000.0,"capex":324200000.0,"dividends_paid":528200000.0,"free_cash_flow":1511500000.0},{"period_end":"2021-03-28","period_type":"Q","operating_cf":2719500000.0,"capex":647900000.0,"dividends_paid":1058000000.0,"free_cash_flow":2071600000.0},{"period_end":"2021-06-27","period_type":"Q","operating_cf":4468400000.0,"capex":985700000.0,"dividends_paid":1588200000.0,"free_cash_flow":3482700000.0},{"period_end":"2021-10-03","period_type":"A","operating_cf":5989100000.0,"capex":1470000000.0,"dividends_paid":2119000000.0,"free_cash_flow":4519100000.0},{"period_end":"2022-01-02","period_type":"Q","operating_cf":1870900000.0,"capex":416800000.0,"dividends_paid":576000000.0,"free_cash_flow":1454100000.0},{"period_end":"2022-04-03","period_type":"Q","operating_cf":2032800000.0,"capex":871900000.0,"dividends_paid":1139200000.0,"free_cash_flow":1160900000.0},{"period_end":"2022-07-03","period_type":"Q","operating_cf":3297600000.0,"capex":1295400000.0,"dividends_paid":1701100000.0,"free_cash_flow":2002200000.0},{"period_end":"2022-10-02","period_type":"A","operating_cf":4397300000.0,"capex":1841300000.0,"dividends_paid":2263300000.0,"free_cash_flow":2556000000.0},{"period_end":"2023-01-01","period_type":"Q","operating_cf":1593200000.0,"capex":516800000.0,"dividends_paid":608300000.0,"free_cash_flow":1076400000.0},{"period_end":"2023-04-02","period_type":"Q","operating_cf":-2360800000.0,"capex":1002000000.0,"dividends_paid":1217400000.0,"free_cash_flow":-3362800000.0},{"period_end":"2023-07-02","period_type":"Q","operating_cf":4063700000.0,"capex":1634100000.0,"dividends_paid":1824800000.0,"free_cash_flow":2429600000.0},{"period_end":"2023-10-01","period_type":"A","operating_cf":6008700000.0,"capex":2333600000.0,"dividends_paid":2431800000.0,"free_cash_flow":3675100000.0},{"period_end":"2023-12-31","period_type":"Q","operating_cf":2383900000.0,"capex":595900000.0,"dividends_paid":648100000.0,"free_cash_flow":1788000000.0},{"period_end":"2024-03-31","period_type":"Q","operating_cf":2889900000.0,"capex":1255000000.0,"dividends_paid":1293500000.0,"free_cash_flow":1634900000.0},{"period_end":"2024-06-30","period_type":"Q","operating_cf":4560000000.0,"capex":1979300000.0,"dividends_paid":1939000000.0,"free_cash_flow":2580700000.0},{"period_end":"2024-09-29","period_type":"A","operating_cf":6095600000.0,"capex":2777500000.0,"dividends_paid":2585000000.0,"free_cash_flow":3318100000.0},{"period_end":"2024-12-29","period_type":"Q","operating_cf":2072000000.0,"capex":692900000.0,"dividends_paid":691900000.0,"free_cash_flow":1379100000.0},{"period_end":"2025-03-30","period_type":"Q","operating_cf":2364000000.0,"capex":1282100000.0,"dividends_paid":1384900000.0,"free_cash_flow":1081900000.0},{"period_end":"2025-06-29","period_type":"Q","operating_cf":3365700000.0,"capex":1849500000.0,"dividends_paid":2078100000.0,"free_cash_flow":1516200000.0},{"period_end":"2025-09-28","period_type":"A","operating_cf":4747500000.0,"capex":2305500000.0,"dividends_paid":2771400000.0,"free_cash_flow":2442000000.0},{"period_end":"2025-12-28","period_type":"Q","operating_cf":1597700000.0,"capex":323700000.0,"dividends_paid":705100000.0,"free_cash_flow":1274000000.0}],"earnings_surprises":[{"earnings_date":"2020-04-28","eps_estimate":0.32,"eps_actual":0.32,"eps_surprise_pct":0.89},{"earnings_date":"2020-07-28","eps_estimate":-0.61,"eps_actual":-0.46,"eps_surprise_pct":24.71},{"earnings_date":"2020-10-29","eps_estimate":0.31,"eps_actual":0.51,"eps_surprise_pct":63.68},{"earnings_date":"2021-01-26","eps_estimate":0.55,"eps_actual":0.61,"eps_surprise_pct":10.28},{"earnings_date":"2021-04-27","eps_estimate":0.53,"eps_actual":0.62,"eps_surprise_pct":16.61},{"earnings_date":"2021-07-27","eps_estimate":0.78,"eps_actual":1.01,"eps_surprise_pct":29.49},{"earnings_date":"2021-10-28","eps_estimate":1.0,"eps_actual":1.0,"eps_surprise_pct":0.45},{"earnings_date":"2022-02-01","eps_estimate":0.8,"eps_actual":0.72,"eps_surprise_pct":-9.45},{"earnings_date":"2022-05-03","eps_estimate":0.6,"eps_actual":0.59,"eps_surprise_pct":-1.02},{"earnings_date":"2022-08-02","eps_estimate":0.76,"eps_actual":0.84,"eps_surprise_pct":11.13},{"earnings_date":"2022-11-03","eps_estimate":0.72,"eps_actual":0.81,"eps_surprise_pct":12.49},{"earnings_date":"2023-02-02","eps_estimate":0.77,"eps_actual":0.75,"eps_surprise_pct":-2.57},{"earnings_date":"2023-05-02","eps_estimate":0.65,"eps_actual":0.74,"eps_surprise_pct":13.12},{"earnings_date":"2023-08-01","eps_estimate":0.95,"eps_actual":1.0,"eps_surprise_pct":5.09},{"earnings_date":"2023-11-02","eps_estimate":0.97,"eps_actual":1.06,"eps_surprise_pct":9.06},{"earnings_date":"2024-01-30","eps_estimate":0.94,"eps_actual":0.9,"eps_surprise_pct":-4.1},{"earnings_date":"2024-04-30","eps_estimate":0.8,"eps_actual":0.68,"eps_surprise_pct":-15.19},{"earnings_date":"2024-07-30","eps_estimate":0.93,"eps_actual":0.93,"eps_surprise_pct":-0.12},{"earnings_date":"2024-10-30","eps_estimate":0.89,"eps_actual":0.8,"eps_surprise_pct":-10.61},{"earnings_date":"2025-01-28","eps_estimate":0.67,"eps_actual":0.69,"eps_surprise_pct":3.46},{"earnings_date":"2025-04-29","eps_estimate":0.48,"eps_actual":0.41,"eps_surprise_pct":-15.23},{"earnings_date":"2025-07-29","eps_estimate":0.65,"eps_actual":0.5,"eps_surprise_pct":-22.49},{"earnings_date":"2025-10-29","eps_estimate":0.56,"eps_actual":0.52,"eps_surprise_pct":-6.51},{"earnings_date":"2026-01-28","eps_estimate":0.59,"eps_actual":0.56,"eps_surprise_pct":-4.59},{"earnings_date":"2026-04-28","eps_estimate":0.4,"eps_actual":null,"eps_surprise_pct":null}]}